DCIM_Macro/rtl/add.v
module add #(
    parameter width = 12      // 默认位宽为12
)(
    input [width-1:0] a,      // 输入a
    input [width-1:0] b,      // 输入b
    input sus,                // 有符号/无符号控制
    output wire [width:0] sum // 加法结果
);

    // 有符号加法：进行符号位扩展
    wire [width:0] a_signed, b_signed;
    
    // 根据sus信号决定是否进行符号扩展
    assign a_signed = sus ? {a[width-1], a} : {1'b0, a};
    assign b_signed = sus ? {b[width-1], b} : {1'b0, b};
    
    // 执行加法
    assign sum = a_signed + b_signed;

endmodule

DCIM_Macro/tb/tb_add.v
`timescale 1ns / 1ps

module tb_add;

    // Parameters
    localparam width = 12;

    // Inputs
    reg [width-1:0] a;
    reg [width-1:0] b;
    reg sus;

    // Outputs
    wire [width:0] sum;

    // Instantiate the Unit Under Test (UUT)
    add #(.width(width)) uut (
        .a(a),
        .b(b),
        .sus(sus),
        .sum(sum)
    );

    integer unsigned_errors = 0;
    integer signed_errors = 0;

    initial begin
        // Initialize Inputs
        a = 0;
        b = 0;
        sus = 0;

        $dumpfile("tb_add.vcd");
        $dumpvars(0, tb_add);

        // --- Test Case 1: Unsigned Addition (sus = 0) ---
        $display("\n--- Test Case 1: Unsigned Addition (sus = 0) ---");
        sus = 0;
        
        // Basic addition
        a = 12'd10; b = 12'd20; #10; 
        $display("Unsigned: %d + %d = %d", a, b, sum);
        if (sum !== 13'd30) begin
            unsigned_errors++;
            $display("  ERROR: Expected 30");
        end
        
        // Overflow case
        a = 12'd4095; b = 12'd1; #10; 
        $display("Unsigned: %d + %d = %d (overflow)", a, b, sum);
        if (sum !== 13'd4096) begin
            unsigned_errors++;
            $display("  ERROR: Expected 4096");
        end
        
        // Max values
        a = 12'hFFF; b = 12'hFFF; #10; 
        $display("Unsigned: %h + %h = %h (max values)", a, b, sum);
        if (sum !== 13'h1FFE) begin
            unsigned_errors++;
            $display("  ERROR: Expected 1FFE");
        end
        
        // Zero values
        a = 12'h000; b = 12'h000; #10; 
        $display("Unsigned: %h + %h = %h (zero values)", a, b, sum);
        if (sum !== 13'd0) begin
            unsigned_errors++;
            $display("  ERROR: Expected 0");
        end

        // --- Test Case 2: Signed Addition (sus = 1) ---
        $display("\n--- Test Case 2: Signed Addition (sus = 1) ---");
        sus = 1;
        
        // Positive + Positive
        a = 12'sd10; b = 12'sd20; #10; 
        $display("Signed: %d + %d = %d", $signed(a), $signed(b), $signed(sum));
        if ($signed(sum) !== 13'sd30) begin
            signed_errors++;
            $display("  ERROR: Expected 30");
        end
        
        // Negative + Positive
        a = -12'sd10; b = 12'sd20; #10; 
        $display("Signed: %d + %d = %d", $signed(a), $signed(b), $signed(sum));
        if ($signed(sum) !== 13'sd10) begin
            signed_errors++;
            $display("  ERROR: Expected 10");
        end
        
        // Positive + Negative
        a = 12'sd10; b = -12'sd20; #10; 
        $display("Signed: %d + %d = %d", $signed(a), $signed(b), $signed(sum));
        if ($signed(sum) !== -13'sd10) begin
            signed_errors++;
            $display("  ERROR: Expected -10");
        end
        
        // Negative + Negative
        a = -12'sd10; b = -12'sd20; #10; 
        $display("Signed: %d + %d = %d", $signed(a), $signed(b), $signed(sum));
        if ($signed(sum) !== -13'sd30) begin
            signed_errors++;
            $display("  ERROR: Expected -30");
        end
        
        // Positive Overflow
        a = 12'sd2047; b = 12'sd1; #10; 
        $display("Signed: %d + %d = %d (pos overflow)", $signed(a), $signed(b), $signed(sum));
        if ($signed(sum) !== 13'sd2048) begin
            signed_errors++;
            $display("  ERROR: Expected 2048");
        end
        
        // Negative Overflow
        a = -12'sd2048; b = -12'sd1; #10; 
        $display("Signed: %d + %d = %d (neg overflow)", $signed(a), $signed(b), $signed(sum));
        if ($signed(sum) !== -13'sd2049) begin
            signed_errors++;
            $display("  ERROR: Expected -2049");
        end
        
        // Max positive values
        a = 12'h7FF; b = 12'h7FF; #10; 
        $display("Signed: %h + %h = %h (max pos)", a, b, sum);
        if ($signed(sum) !== 13'sh0FFE) begin
            signed_errors++;
            $display("  ERROR: Expected 0FFE");
        end
        
        // Max negative values
        a = 12'h800; b = 12'h800; #10; 
        $display("Signed: %h + %h = %h (max neg)", a, b, sum);
        if ($signed(sum) !== 13'sh1000) begin
            signed_errors++;
            $display("  ERROR: Expected 1000");
        end

        // --- Test Case 3: Random Unsigned Addition ---
        $display("\n--- Test Case 3: Random Unsigned Addition ---");
        sus = 0;
        repeat(5) begin
            a = $random;
            b = $random;
            #10;
            $display("Random Unsigned: %d + %d = %d (expected %d)", 
                     a, b, sum, a + b);
            if (sum !== (a + b)) begin
                unsigned_errors++;
                $display("  ERROR: Mismatch detected");
            end
        end

        // --- Test Case 4: Random Signed Addition ---
        $display("\n--- Test Case 4: Random Signed Addition ---");
        sus = 1;
        repeat(5) begin
            a = $random;
            b = $random;
            #10;
            $display("Random Signed: %d + %d = %d (expected %d)", 
                     $signed(a), $signed(b), $signed(sum), 
                     $signed(a) + $signed(b));
            if ($signed(sum) !== ($signed(a) + $signed(b))) begin
                signed_errors++;
                $display("  ERROR: Mismatch detected");
            end
        end

        // Final results
        #20;
        $display("\n--- Test Summary ---");
        $display("Unsigned tests: %0d errors", unsigned_errors);
        $display("Signed tests: %0d errors", signed_errors);
        
        if ((unsigned_errors == 0) && (signed_errors == 0)) begin
            $display("--- ALL TESTS PASSED ---");
        end else begin
            $display("--- TEST FAILURES DETECTED ---");
        end

        $finish;
    end

endmodule

DCIM_Macro/tb_add.vcd
$date
	Fri Aug 08 19:20:53 2025
$end
$version
	Icarus Verilog
$end
$timescale
	1ps
$end
$scope module tb_add $end
$var wire 13 ! sum [12:0] $end
$var parameter 32 " width $end
$var reg 12 # a [11:0] $end
$var reg 12 $ b [11:0] $end
$var reg 1 % sus $end
$var integer 32 & signed_errors [31:0] $end
$var integer 32 ' unsigned_errors [31:0] $end
$scope module uut $end
$var wire 12 ( a [11:0] $end
$var wire 12 ) b [11:0] $end
$var wire 1 % sus $end
$var wire 13 * sum [12:0] $end
$var wire 13 + b_signed [12:0] $end
$var wire 13 , a_signed [12:0] $end
$var parameter 32 - width $end
$upscope $end
$upscope $end
$enddefinitions $end
$comment Show the parameter values. $end
$dumpall
b1100 -
b1100 "
$end
#0
$dumpvars
b1010 ,
b10100 +
b11110 *
b10100 )
b1010 (
b0 '
b0 &
0%
b10100 $
b1010 #
b11110 !
$end
#10000
b1 +
b1000000000000 !
b1000000000000 *
b111111111111 ,
b1 $
b1 )
b111111111111 #
b111111111111 (
#20000
b1111111111110 !
b1111111111110 *
b111111111111 +
b111111111111 $
b111111111111 )
#30000
b0 +
b0 !
b0 *
b0 ,
b0 $
b0 )
b0 #
b0 (
#40000
b1010 ,
b11110 !
b11110 *
b10100 +
b10100 $
b10100 )
b1010 #
b1010 (
1%
#50000
b1010 !
b1010 *
b1111111110110 ,
b111111110110 #
b111111110110 (
#60000
b1111111101100 +
b1111111110110 !
b1111111110110 *
b1010 ,
b111111101100 $
b111111101100 )
b1010 #
b1010 (
#70000
b1111111100010 !
b1111111100010 *
b1111111110110 ,
b111111110110 #
b111111110110 (
#80000
b1 +
b100000000000 !
b100000000000 *
b11111111111 ,
b1 $
b1 )
b11111111111 #
b11111111111 (
#90000
b1111111111111 +
b1011111111111 !
b1011111111111 *
b1100000000000 ,
b111111111111 $
b111111111111 )
b100000000000 #
b100000000000 (
#100000
b11111111111 +
b111111111110 !
b111111111110 *
b11111111111 ,
b11111111111 $
b11111111111 )
b11111111111 #
b11111111111 (
#110000
b1100000000000 +
b1000000000000 !
b1000000000000 *
b1100000000000 ,
b100000000000 $
b100000000000 )
b100000000000 #
b100000000000 (
#120000
b10100100100 ,
b1001110100101 !
b1001110100101 *
b111010000001 +
b111010000001 $
b111010000001 )
b10100100100 #
b10100100100 (
0%
#130000
b11001100011 +
b110001101100 !
b110001101100 *
b11000001001 ,
b11001100011 $
b11001100011 )
b11000001001 #
b11000001001 (
#140000
b100110001101 +
b1010010011010 !
b1010010011010 *
b101100001101 ,
b100110001101 $
b100110001101 )
b101100001101 #
b101100001101 (
#150000
b1000010010 +
b11001110111 !
b11001110111 *
b10001100101 ,
b1000010010 $
b1000010010 )
b10001100101 #
b10001100101 (
#160000
b110100001101 +
b1000000001110 !
b1000000001110 *
b1100000001 ,
b110100001101 $
b110100001101 )
b1100000001 #
b1100000001 (
#170000
b101110110 ,
b1111010110011 !
b1111010110011 *
b1110100111101 +
b110100111101 $
b110100111101 )
b101110110 #
b101110110 (
1%
#180000
b11110001100 +
b111101111001 !
b111101111001 *
b11111101101 ,
b11110001100 $
b11110001100 )
b11111101101 #
b11111101101 (
#190000
b10011000110 +
b1111010111111 !
b1111010111111 *
b1100111111001 ,
b10011000110 $
b10011000110 )
b100111111001 #
b100111111001 (
#200000
b1010101010 +
b11101101111 !
b11101101111 *
b10011000101 ,
b1010101010 $
b1010101010 )
b10011000101 #
b10011000101 (
#210000
b1001110111 +
b101001011100 !
b101001011100 *
b11111100101 ,
b1001110111 $
b1001110111 )
b11111100101 #
b11111100101 (
