DCIM_Macro/rtl/s_cla.v
// 最终的、高性能的24位分块先行进位加法器 (s_cla) - 完全展开版本
module s_cla(
    input [23:0] a,
    input [23:0] b,
    input cin,
    output [23:0] sum
);

    // --- 信号定义 ---
    wire [23:0] g, p;
    wire [5:0]  bg, bp;
    wire [6:0]  c_block;
    wire [24:0] c; // 最终的逐位进位

    // --- 1. 计算每一位的 g 和 p ---
    assign g = a & b;
    assign p = a ^ b;

    // --- 2. 计算每个4-bit块的 bg 和 bp ---
    assign bg[0] = g[3] | (p[3] & g[2]) | (p[3] & p[2] & g[1]) | (p[3] & p[2] & p[1] & g[0]);
    assign bp[0] = p[3] & p[2] & p[1] & p[0];
    assign bg[1] = g[7] | (p[7] & g[6]) | (p[7] & p[6] & g[5]) | (p[7] & p[6] & p[5] & g[4]);
    assign bp[1] = p[7] & p[6] & p[5] & p[4];
    assign bg[2] = g[11] | (p[11] & g[10]) | (p[11] & p[10] & g[9]) | (p[11] & p[10] & p[9] & g[8]);
    assign bp[2] = p[11] & p[10] & p[9] & p[8];
    assign bg[3] = g[15] | (p[15] & g[14]) | (p[15] & p[14] & g[13]) | (p[15] & p[14] & p[13] & g[12]);
    assign bp[3] = p[15] & p[14] & p[13] & p[12];
    assign bg[4] = g[19] | (p[19] & g[18]) | (p[19] & p[18] & g[17]) | (p[19] & p[18] & p[17] & g[16]);
    assign bp[4] = p[19] & p[18] & p[17] & p[16];
    assign bg[5] = g[23] | (p[23] & g[22]) | (p[23] & p[22] & g[21]) | (p[23] & p[22] & p[21] & g[20]);
    assign bp[5] = p[23] & p[22] & p[21] & p[20];

    // --- 3. 计算块间进位 ---
    assign c_block[0] = cin;
    assign c_block[1] = bg[0] | (bp[0] & c_block[0]);
    assign c_block[2] = bg[1] | (bp[1] & c_block[1]);
    assign c_block[3] = bg[2] | (bp[2] & c_block[2]);
    assign c_block[4] = bg[3] | (bp[3] & c_block[3]);
    assign c_block[5] = bg[4] | (bp[4] & c_block[4]);
    assign c_block[6] = bg[5] | (bp[5] & c_block[5]);

    // --- 4. 计算最终的逐位进位 c[24:0] ---
    assign c[0] = c_block[0];
    assign c[1] = g[0] | (p[0] & c[0]);
    assign c[2] = g[1] | (p[1] & c[1]);
    assign c[3] = g[2] | (p[2] & c[2]);
    assign c[4] = c_block[1];
    assign c[5] = g[4] | (p[4] & c[4]);
    assign c[6] = g[5] | (p[5] & c[5]);
    assign c[7] = g[6] | (p[6] & c[6]);
    assign c[8] = c_block[2];
    assign c[9] = g[8] | (p[8] & c[8]);
    assign c[10] = g[9] | (p[9] & c[9]);
    assign c[11] = g[10] | (p[10] & c[10]);
    assign c[12] = c_block[3];
    assign c[13] = g[12] | (p[12] & c[12]);
    assign c[14] = g[13] | (p[13] & c[13]);
    assign c[15] = g[14] | (p[14] & c[14]);
    assign c[16] = c_block[4];
    assign c[17] = g[16] | (p[16] & c[16]);
    assign c[18] = g[17] | (p[17] & c[17]);
    assign c[19] = g[18] | (p[18] & c[18]);
    assign c[20] = c_block[5];
    assign c[21] = g[20] | (p[20] & c[20]);
    assign c[22] = g[21] | (p[21] & c[21]);
    assign c[23] = g[22] | (p[22] & c[22]);
    assign c[24] = c_block[6]; // Final carry-out

    // --- 5. 计算最终的和 (sum) ---
    assign sum = p ^ c[23:0];

endmodule

DCIM_Macro/rtl/add.v
module add #(
    parameter width = 12      // 默认位宽为12
)(
    input [width-1:0] a,      // 输入a
    input [width-1:0] b,      // 输入b
    input sus,                // 有符号/无符号控制
    output wire [width:0] sum // 加法结果
);

    // 有符号加法：进行符号位扩展
    wire [width:0] a_signed, b_signed;
    
    // 根据sus信号决定是否进行符号扩展
    assign a_signed = sus ? {a[width-1], a} : {1'b0, a};
    assign b_signed = sus ? {b[width-1], b} : {1'b0, b};
    
    // 执行加法
    assign sum = a_signed + b_signed;

endmodule

DCIM_Macro/rtl/se_cla.v
module se_cla(
    input [26:0] a,           // 27位输入
    input [50:0] b,           // 51位输入
    output [50:0] sum         // 51位输出
);

    // 对27位输入a进行符号位扩展
    wire [50:0] a_ext;
    assign a_ext = {{24{a[26]}}, a};  // 符号位扩展
    
    // 低27位加法
    wire [26:0] sum_low;
    wire carry_out;
    
    add #(.width(27)) add_low(
        .a(a),
        .b(b[26:0]),
        .sus(1'b0),  // 无符号加法
        .sum({carry_out, sum_low})
    );
    
    // 高24位加法（考虑进位）
    wire [23:0] sum_high;
    
    s_cla s_cla_inst(
        .a(a_ext[50:27]),
        .b(b[50:27]),
        .cin(carry_out),
        .sum(sum_high)
    );
    
    // 拼接结果
    assign sum = {sum_high, sum_low};

endmodule

DCIM_Macro/rtl/accumulator.v
// 最终的、实例化se_cla的、电路稳定的累加器
module accumulator(
    input [26:0] a,
    input clk,
    input acm_en,
    input rstn,
    input st,
    output [50:0] nout
);

    // 内部累加寄存器
    reg [50:0] nout_1;
    
    // 模块输出直接来自寄存器
    assign nout = nout_1;

    // --- 用于计算的中间信号 ---
    wire [50:0] shifted_nout_1; // 用于存放 nout_1 << 1 的结果
    wire [50:0] sum_result;     // 加法器的输出

    // --- 组合逻辑部分 ---
    // 1. 对当前寄存器的值进行左移一位
    assign shifted_nout_1 = {nout_1[49:0], 1'b0};

    // 2. 实例化 se_cla 加法器来计算：(nout_1 << 1) + a
    se_cla se_cla_inst (
        .a(a),
        .b(shifted_nout_1),
        .sum(sum_result)
    );

    // --- 时序逻辑部分 ---
    // 在时钟边沿，用预先计算好的、稳定的加法结果来更新寄存器
    always @(posedge clk or negedge rstn) begin
        if (!rstn) begin
            nout_1 <= 51'b0;
        end else if (acm_en) begin
            if (st) begin
                nout_1 <= 51'b0;
            end else begin
                // 锁存稳定的加法结果
                nout_1 <= sum_result;
            end
        end
    end

endmodule

DCIM_Macro/tb/tb_accumulator.v
`timescale 1ns / 1ps

module tb_accumulator;

    // Inputs
    reg [26:0] a;
    reg clk;
    reg acm_en;
    reg rstn;
    reg st;

    // Outputs
    wire [50:0] nout;

    // Instantiate the Unit Under Test (UUT)
    accumulator uut (
        .a(a),
        .clk(clk),
        .acm_en(acm_en),
        .rstn(rstn),
        .st(st),
        .nout(nout)
    );

    // Clock generation
    initial begin
        clk = 0;
        forever #5 clk = ~clk;
    end

    // Declare variables outside of initial block
    integer i, j;
    reg [50:0] expected_nout;

    initial begin
        // Initialize Inputs
        a = 0;
        acm_en = 0;
        rstn = 0;
        st = 1;

        $dumpfile("tb_accumulator.vcd");
        $dumpvars(0, tb_accumulator);
        $monitor("Time=%0t rstn=%b acm_en=%b st=%b a=%d nout=%d", 
                 $time, rstn, acm_en, st, a, nout);

        // Test Case 1: Reset
        $display("\n--- Test Case 1: Reset ---");
        #10;
        rstn = 1;
        #10;
        $display("Reset released. nout should be 0. nout = %d", nout);

        // Test Case 2: Accumulation disabled
        $display("\n--- Test Case 2: Accumulation disabled (acm_en=0) ---");
        acm_en = 0;
        st = 0;
        a = 100;
        #20; // Wait for a few clock cycles
        $display("nout should remain 0. nout = %d", nout);

        // Test Case 3: Accumulation enabled and running
        $display("\n--- Test Case 3: Accumulation enabled and running ---");
        acm_en = 1;
        st = 0;
        a = 10; @(posedge clk); #1; // Cycle 1: nout = (0 << 1) + 10 = 10
        $display("Cycle 1: a=%d, nout=%d", 10, nout);
        a = 20; @(posedge clk); #1; // Cycle 2: nout = (10 << 1) + 20 = 40
        $display("Cycle 2: a=%d, nout=%d", 20, nout);
        a = 30; @(posedge clk); #1; // Cycle 3: nout = (40 << 1) + 30 = 110
        $display("Cycle 3: a=%d, nout=%d", 30, nout);
        a = 0; @(posedge clk); #1; // Cycle 4: nout = (110 << 1) + 0 = 220
        $display("Cycle 4: a=%d, nout=%d", 0, nout);

        // Test Case 4: 'st' signal stops and resets accumulation
        $display("\n--- Test Case 4: 'st' signal high ---");
        st = 1;
        a = 999; // This value should be ignored
        @(posedge clk); #1;
        $display("st is high, nout should reset to 0. nout = %d", nout);
        st = 0;
        a = 5;
        @(posedge clk); #1;
        $display("st is low again, accumulation starts from 0. nout = %d", nout);

        // Test Case 5: Negative reset
        $display("\n--- Test Case 5: Negative reset (rstn=0) ---");
        rstn = 0;
        #10;
        $display("rstn is low, nout should reset to 0. nout = %d", nout);
        rstn = 1; // Release reset for next test
        #10;

        // Test Case 6: Long accumulation sequence
        $display("\n--- Test Case 6: Long accumulation sequence ---");
        st = 1; @(posedge clk); #1; // Reset accumulator
        st = 0;
        acm_en = 1;
        
        expected_nout = 0;
        
        for (i = 1; i <= 10; i = i + 1) begin
            a = i;
            expected_nout = (expected_nout << 1) + i;
            @(posedge clk); #1;
            $display("Cycle %0d: a=%d, nout=%d (expected %d)", 
                     i, i, nout, expected_nout);
        end

        // Test Case 7: Overflow test
        $display("\n--- Test Case 7: Overflow Test ---");
        st = 1; @(posedge clk); #1; // Reset accumulator
        st = 0;
        a = 27'h7FFFFFF; // Max positive value (134,217,727)
        expected_nout = 0;
        
        @(posedge clk); #1;
        expected_nout = (expected_nout << 1) + a;
        $display("First value loaded: nout = %h (expected %h)", 
                 nout, expected_nout);
        
        // Add large numbers to force overflow
        for (j = 0; j < 5; j = j + 1) begin
            a = 27'h7FFFFFF;
            expected_nout = (expected_nout << 1) + a;
            @(posedge clk); #1;
            $display("Cycle %0d: nout = %h (expected %h)", 
                     j+1, nout, expected_nout);
        end

        #20;
        $finish;
    end

endmodule

DCIM_Macro/tb_accumulator.vcd
$date
	Fri Aug 08 19:20:59 2025
$end
$version
	Icarus Verilog
$end
$timescale
	1ps
$end
$scope module tb_accumulator $end
$var wire 51 ! nout [50:0] $end
$var reg 27 " a [26:0] $end
$var reg 1 # acm_en $end
$var reg 1 $ clk $end
$var reg 51 % expected_nout [50:0] $end
$var reg 1 & rstn $end
$var reg 1 ' st $end
$var integer 32 ( i [31:0] $end
$var integer 32 ) j [31:0] $end
$scope module uut $end
$var wire 27 * a [26:0] $end
$var wire 1 # acm_en $end
$var wire 1 $ clk $end
$var wire 51 + nout [50:0] $end
$var wire 1 & rstn $end
$var wire 1 ' st $end
$var wire 51 , sum_result [50:0] $end
$var wire 51 - shifted_nout_1 [50:0] $end
$var reg 51 . nout_1 [50:0] $end
$scope module se_cla_inst $end
$var wire 27 / a [26:0] $end
$var wire 51 0 b [50:0] $end
$var wire 27 1 sum_low [26:0] $end
$var wire 24 2 sum_high [23:0] $end
$var wire 51 3 sum [50:0] $end
$var wire 1 4 carry_out $end
$var wire 51 5 a_ext [50:0] $end
$scope module add_low $end
$var wire 27 6 a [26:0] $end
$var wire 28 7 a_signed [27:0] $end
$var wire 27 8 b [26:0] $end
$var wire 28 9 b_signed [27:0] $end
$var wire 1 : sus $end
$var wire 28 ; sum [27:0] $end
$var parameter 32 < width $end
$upscope $end
$scope module s_cla_inst $end
$var wire 24 = a [23:0] $end
$var wire 24 > b [23:0] $end
$var wire 1 4 cin $end
$var wire 24 ? g [23:0] $end
$var wire 24 @ p [23:0] $end
$var wire 24 A sum [23:0] $end
$var wire 7 B c_block [6:0] $end
$var wire 25 C c [24:0] $end
$var wire 6 D bp [5:0] $end
$var wire 6 E bg [5:0] $end
$upscope $end
$upscope $end
$upscope $end
$upscope $end
$enddefinitions $end
$comment Show the parameter values. $end
$dumpall
b11011 <
$end
#0
$dumpvars
b0 E
b0 D
b0 C
b0 B
b0 A
b0 @
b0 ?
b0 >
b0 =
b0 ;
0:
b0 9
b0 8
b0 7
b0 6
b0 5
04
b0 3
b0 2
b0 1
b0 0
b0 /
b0 .
b0 -
b0 ,
b0 +
b0 *
bx )
bx (
1'
0&
bx %
0$
0#
b0 "
b0 !
$end
#5000
1$
#10000
0$
1&
#15000
1$
#20000
b1100100 ,
b1100100 3
b1100100 1
0$
b1100100 5
b1100100 ;
b1100100 7
b1100100 "
b1100100 *
b1100100 /
b1100100 6
0'
#25000
1$
#30000
0$
#35000
1$
#40000
b1010 ,
b1010 3
b1010 1
0$
b1010 5
b1010 ;
b1010 7
b1010 "
b1010 *
b1010 /
b1010 6
1#
#45000
b11110 ,
b11110 3
b11110 1
b11110 ;
b10100 9
b10100 8
b10100 -
b10100 0
b1010 !
b1010 +
b1010 .
1$
#46000
b101000 ,
b101000 3
b101000 1
b10100 5
b101000 ;
b10100 7
b10100 "
b10100 *
b10100 /
b10100 6
#50000
0$
#55000
b1100100 ,
b1100100 3
b1100100 1
b1100100 ;
b1010000 9
b1010000 8
b1010000 -
b1010000 0
b101000 !
b101000 +
b101000 .
1$
#56000
b1101110 ,
b1101110 3
b1101110 1
b11110 5
b1101110 ;
b11110 7
b11110 "
b11110 *
b11110 /
b11110 6
#60000
0$
#65000
b11111010 ,
b11111010 3
b11111010 1
b11111010 ;
b11011100 9
b11011100 8
b11011100 -
b11011100 0
b1101110 !
b1101110 +
b1101110 .
1$
#66000
b11011100 ,
b11011100 3
b11011100 1
b0 5
b11011100 ;
b0 7
b0 "
b0 *
b0 /
b0 6
#70000
0$
#75000
b110111000 ,
b110111000 3
b110111000 1
b110111000 ;
b110111000 9
b110111000 8
b110111000 -
b110111000 0
b11011100 !
b11011100 +
b11011100 .
1$
#76000
b10110011111 ,
b10110011111 3
b10110011111 1
b1111100111 5
b10110011111 ;
b1111100111 7
b1111100111 "
b1111100111 *
b1111100111 /
b1111100111 6
1'
#80000
0$
#85000
b1111100111 ,
b1111100111 3
b1111100111 1
b1111100111 ;
b0 9
b0 8
b0 -
b0 0
b0 !
b0 +
b0 .
1$
#86000
b101 ,
b101 3
b101 1
b101 5
b101 ;
b101 7
b101 "
b101 *
b101 /
b101 6
0'
#90000
0$
#95000
b1111 ,
b1111 3
b1111 1
b1111 ;
b1010 9
b1010 8
b1010 -
b1010 0
b101 !
b101 +
b101 .
1$
#96000
b101 ,
b101 3
b101 1
b101 ;
b0 9
b0 8
b0 -
b0 0
b0 !
b0 +
b0 .
0&
#100000
0$
#105000
1$
#106000
1&
#110000
0$
#115000
b1111 ,
b1111 3
b1111 1
b1111 ;
b1010 9
b1010 8
b1010 -
b1010 0
b101 !
b101 +
b101 .
1$
#116000
1'
#120000
0$
#125000
b101 ,
b101 3
b101 1
b101 ;
b0 9
b0 8
b0 -
b0 0
b0 !
b0 +
b0 .
1$
#126000
b1 ,
b1 3
b1 1
b1 5
b1 ;
b1 7
b1 "
b1 *
b1 /
b1 6
b1 (
b1 %
0'
#130000
0$
#135000
b11 ,
b11 3
b11 1
b11 ;
b10 9
b10 8
b10 -
b10 0
b1 !
b1 +
b1 .
1$
#136000
b100 ,
b100 3
b100 1
b100 %
b10 5
b100 ;
b10 7
b10 "
b10 *
b10 /
b10 6
b10 (
#140000
0$
#145000
b1010 ,
b1010 3
b1010 1
b1010 ;
b1000 9
b1000 8
b1000 -
b1000 0
b100 !
b100 +
b100 .
1$
#146000
b1011 ,
b1011 3
b1011 1
b1011 %
b11 5
b1011 ;
b11 7
b11 "
b11 *
b11 /
b11 6
b11 (
#150000
0$
#155000
b11001 ,
b11001 3
b11001 1
b11001 ;
b10110 9
b10110 8
b10110 -
b10110 0
b1011 !
b1011 +
b1011 .
1$
#156000
b11010 ,
b11010 3
b11010 1
b11010 %
b100 5
b11010 ;
b100 7
b100 "
b100 *
b100 /
b100 6
b100 (
#160000
0$
#165000
b111000 ,
b111000 3
b111000 1
b111000 ;
b110100 9
b110100 8
b110100 -
b110100 0
b11010 !
b11010 +
b11010 .
1$
#166000
b111001 ,
b111001 3
b111001 1
b111001 %
b101 5
b111001 ;
b101 7
b101 "
b101 *
b101 /
b101 6
b101 (
#170000
0$
#175000
b1110111 ,
b1110111 3
b1110111 1
b1110111 ;
b1110010 9
b1110010 8
b1110010 -
b1110010 0
b111001 !
b111001 +
b111001 .
1$
#176000
b1111000 ,
b1111000 3
b1111000 1
b1111000 %
b110 5
b1111000 ;
b110 7
b110 "
b110 *
b110 /
b110 6
b110 (
#180000
0$
#185000
b11110110 ,
b11110110 3
b11110110 1
b11110110 ;
b11110000 9
b11110000 8
b11110000 -
b11110000 0
b1111000 !
b1111000 +
b1111000 .
1$
#186000
b11110111 ,
b11110111 3
b11110111 1
b11110111 %
b111 5
b11110111 ;
b111 7
b111 "
b111 *
b111 /
b111 6
b111 (
#190000
0$
#195000
b111110101 ,
b111110101 3
b111110101 1
b111110101 ;
b111101110 9
b111101110 8
b111101110 -
b111101110 0
b11110111 !
b11110111 +
b11110111 .
1$
#196000
b111110110 ,
b111110110 3
b111110110 1
b111110110 %
b1000 5
b111110110 ;
b1000 7
b1000 "
b1000 *
b1000 /
b1000 6
b1000 (
#200000
0$
#205000
b1111110100 ,
b1111110100 3
b1111110100 1
b1111110100 ;
b1111101100 9
b1111101100 8
b1111101100 -
b1111101100 0
b111110110 !
b111110110 +
b111110110 .
1$
#206000
b1111110101 ,
b1111110101 3
b1111110101 1
b1111110101 %
b1001 5
b1111110101 ;
b1001 7
b1001 "
b1001 *
b1001 /
b1001 6
b1001 (
#210000
0$
#215000
b11111110011 ,
b11111110011 3
b11111110011 1
b11111110011 ;
b11111101010 9
b11111101010 8
b11111101010 -
b11111101010 0
b1111110101 !
b1111110101 +
b1111110101 .
1$
#216000
b11111110100 ,
b11111110100 3
b11111110100 1
b11111110100 %
b1010 5
b11111110100 ;
b1010 7
b1010 "
b1010 *
b1010 /
b1010 6
b1010 (
#220000
0$
#225000
b111111110010 ,
b111111110010 3
b111111110010 1
b111111110010 ;
b111111101000 9
b111111101000 8
b111111101000 -
b111111101000 0
b11111110100 !
b11111110100 +
b11111110100 .
1$
#226000
1'
b1011 (
#230000
0$
#235000
b1010 ,
b1010 3
b1010 1
b1010 ;
b0 9
b0 8
b0 -
b0 0
b0 !
b0 +
b0 .
1$
#236000
b111111 D
b111111111111111111111111 2
b111111111111111111111111 A
b111111111111111111111111 @
b111111111111111111111111 =
b111111111111111111111111111111111111111111111111111 ,
b111111111111111111111111111111111111111111111111111 3
b111111111111111111111111111 1
b0 %
b111111111111111111111111111111111111111111111111111 5
b111111111111111111111111111 ;
b111111111111111111111111111 7
b111111111111111111111111111 "
b111111111111111111111111111 *
b111111111111111111111111111 /
b111111111111111111111111111 6
0'
#240000
0$
#245000
b111111 E
b0 D
b1111111111111111111111111 C
b111111111111111111111111 2
b111111111111111111111111 A
b111111111111111111111111111111111111111111111111101 ,
b111111111111111111111111111111111111111111111111101 3
b111111111111111111111111101 1
b1111111 B
14
b111111111111111111111111 ?
b0 @
b1111111111111111111111111101 ;
b111111111111111111111111110 9
b111111111111111111111111110 8
b111111111111111111111111 >
b111111111111111111111111111111111111111111111111110 -
b111111111111111111111111111111111111111111111111110 0
b111111111111111111111111111111111111111111111111111 !
b111111111111111111111111111111111111111111111111111 +
b111111111111111111111111111111111111111111111111111 .
1$
#246000
b0 )
b10111111111111111111111111101 %
#250000
0$
#255000
b111111111111111111111111111111111111111111111111001 ,
b111111111111111111111111111111111111111111111111001 3
b111111111111111111111111001 1
b1111111111111111111111111001 ;
b111111111111111111111111010 9
b111111111111111111111111010 8
b111111111111111111111111111111111111111111111111010 -
b111111111111111111111111111111111111111111111111010 0
b111111111111111111111111111111111111111111111111101 !
b111111111111111111111111111111111111111111111111101 +
b111111111111111111111111111111111111111111111111101 .
1$
#256000
b110111111111111111111111111001 %
b1 )
#260000
0$
#265000
b111111111111111111111111111111111111111111111110001 ,
b111111111111111111111111111111111111111111111110001 3
b111111111111111111111110001 1
b1111111111111111111111110001 ;
b111111111111111111111110010 9
b111111111111111111111110010 8
b111111111111111111111111111111111111111111111110010 -
b111111111111111111111111111111111111111111111110010 0
b111111111111111111111111111111111111111111111111001 !
b111111111111111111111111111111111111111111111111001 +
b111111111111111111111111111111111111111111111111001 .
1$
#266000
b1110111111111111111111111110001 %
b10 )
#270000
0$
#275000
b111111111111111111111111111111111111111111111100001 ,
b111111111111111111111111111111111111111111111100001 3
b111111111111111111111100001 1
b1111111111111111111111100001 ;
b111111111111111111111100010 9
b111111111111111111111100010 8
b111111111111111111111111111111111111111111111100010 -
b111111111111111111111111111111111111111111111100010 0
b111111111111111111111111111111111111111111111110001 !
b111111111111111111111111111111111111111111111110001 +
b111111111111111111111111111111111111111111111110001 .
1$
#276000
b11110111111111111111111111100001 %
b11 )
#280000
0$
#285000
b111111111111111111111111111111111111111111111000001 ,
b111111111111111111111111111111111111111111111000001 3
b111111111111111111111000001 1
b1111111111111111111111000001 ;
b111111111111111111111000010 9
b111111111111111111111000010 8
b111111111111111111111111111111111111111111111000010 -
b111111111111111111111111111111111111111111111000010 0
b111111111111111111111111111111111111111111111100001 !
b111111111111111111111111111111111111111111111100001 +
b111111111111111111111111111111111111111111111100001 .
1$
#286000
b111110111111111111111111111000001 %
b100 )
#290000
0$
#295000
b111111111111111111111111111111111111111111110000001 ,
b111111111111111111111111111111111111111111110000001 3
b111111111111111111110000001 1
b1111111111111111111110000001 ;
b111111111111111111110000010 9
b111111111111111111110000010 8
b111111111111111111111111111111111111111111110000010 -
b111111111111111111111111111111111111111111110000010 0
b111111111111111111111111111111111111111111111000001 !
b111111111111111111111111111111111111111111111000001 +
b111111111111111111111111111111111111111111111000001 .
1$
#296000
b101 )
#300000
0$
#305000
b111111111111111111111111111111111111111111100000001 ,
b111111111111111111111111111111111111111111100000001 3
b111111111111111111100000001 1
b1111111111111111111100000001 ;
b111111111111111111100000010 9
b111111111111111111100000010 8
b111111111111111111111111111111111111111111100000010 -
b111111111111111111111111111111111111111111100000010 0
b111111111111111111111111111111111111111111110000001 !
b111111111111111111111111111111111111111111110000001 +
b111111111111111111111111111111111111111111110000001 .
1$
#310000
0$
#315000
b111111111111111111111111111111111111111111000000001 ,
b111111111111111111111111111111111111111111000000001 3
b111111111111111111000000001 1
b1111111111111111111000000001 ;
b111111111111111111000000010 9
b111111111111111111000000010 8
b111111111111111111111111111111111111111111000000010 -
b111111111111111111111111111111111111111111000000010 0
b111111111111111111111111111111111111111111100000001 !
b111111111111111111111111111111111111111111100000001 +
b111111111111111111111111111111111111111111100000001 .
1$
