DCIM_Macro/rtl/s_cla.v
// 最终的、高性能的24位分块先行进位加法器 (s_cla) - 完全展开版本
module s_cla(
    input [23:0] a,
    input [23:0] b,
    input cin,
    output [23:0] sum
);

    // --- 信号定义 ---
    wire [23:0] g, p;
    wire [5:0]  bg, bp;
    wire [6:0]  c_block;
    wire [24:0] c; // 最终的逐位进位

    // --- 1. 计算每一位的 g 和 p ---
    assign g = a & b;
    assign p = a ^ b;

    // --- 2. 计算每个4-bit块的 bg 和 bp ---
    assign bg[0] = g[3] | (p[3] & g[2]) | (p[3] & p[2] & g[1]) | (p[3] & p[2] & p[1] & g[0]);
    assign bp[0] = p[3] & p[2] & p[1] & p[0];
    assign bg[1] = g[7] | (p[7] & g[6]) | (p[7] & p[6] & g[5]) | (p[7] & p[6] & p[5] & g[4]);
    assign bp[1] = p[7] & p[6] & p[5] & p[4];
    assign bg[2] = g[11] | (p[11] & g[10]) | (p[11] & p[10] & g[9]) | (p[11] & p[10] & p[9] & g[8]);
    assign bp[2] = p[11] & p[10] & p[9] & p[8];
    assign bg[3] = g[15] | (p[15] & g[14]) | (p[15] & p[14] & g[13]) | (p[15] & p[14] & p[13] & g[12]);
    assign bp[3] = p[15] & p[14] & p[13] & p[12];
    assign bg[4] = g[19] | (p[19] & g[18]) | (p[19] & p[18] & g[17]) | (p[19] & p[18] & p[17] & g[16]);
    assign bp[4] = p[19] & p[18] & p[17] & p[16];
    assign bg[5] = g[23] | (p[23] & g[22]) | (p[23] & p[22] & g[21]) | (p[23] & p[22] & p[21] & g[20]);
    assign bp[5] = p[23] & p[22] & p[21] & p[20];

    // --- 3. 计算块间进位 ---
    assign c_block[0] = cin;
    assign c_block[1] = bg[0] | (bp[0] & c_block[0]);
    assign c_block[2] = bg[1] | (bp[1] & c_block[1]);
    assign c_block[3] = bg[2] | (bp[2] & c_block[2]);
    assign c_block[4] = bg[3] | (bp[3] & c_block[3]);
    assign c_block[5] = bg[4] | (bp[4] & c_block[4]);
    assign c_block[6] = bg[5] | (bp[5] & c_block[5]);

    // --- 4. 计算最终的逐位进位 c[24:0] ---
    assign c[0] = c_block[0];
    assign c[1] = g[0] | (p[0] & c[0]);
    assign c[2] = g[1] | (p[1] & c[1]);
    assign c[3] = g[2] | (p[2] & c[2]);
    assign c[4] = c_block[1];
    assign c[5] = g[4] | (p[4] & c[4]);
    assign c[6] = g[5] | (p[5] & c[5]);
    assign c[7] = g[6] | (p[6] & c[6]);
    assign c[8] = c_block[2];
    assign c[9] = g[8] | (p[8] & c[8]);
    assign c[10] = g[9] | (p[9] & c[9]);
    assign c[11] = g[10] | (p[10] & c[10]);
    assign c[12] = c_block[3];
    assign c[13] = g[12] | (p[12] & c[12]);
    assign c[14] = g[13] | (p[13] & c[13]);
    assign c[15] = g[14] | (p[14] & c[14]);
    assign c[16] = c_block[4];
    assign c[17] = g[16] | (p[16] & c[16]);
    assign c[18] = g[17] | (p[17] & c[17]);
    assign c[19] = g[18] | (p[18] & c[18]);
    assign c[20] = c_block[5];
    assign c[21] = g[20] | (p[20] & c[20]);
    assign c[22] = g[21] | (p[21] & c[21]);
    assign c[23] = g[22] | (p[22] & c[22]);
    assign c[24] = c_block[6]; // Final carry-out

    // --- 5. 计算最终的和 (sum) ---
    assign sum = p ^ c[23:0];

endmodule

DCIM_Macro/rtl/add.v
module add #(
    parameter width = 12      // 默认位宽为12
)(
    input [width-1:0] a,      // 输入a
    input [width-1:0] b,      // 输入b
    input sus,                // 有符号/无符号控制
    output wire [width:0] sum // 加法结果
);

    // 有符号加法：进行符号位扩展
    wire [width:0] a_signed, b_signed;
    
    // 根据sus信号决定是否进行符号扩展
    assign a_signed = sus ? {a[width-1], a} : {1'b0, a};
    assign b_signed = sus ? {b[width-1], b} : {1'b0, b};
    
    // 执行加法
    assign sum = a_signed + b_signed;

endmodule

DCIM_Macro/rtl/se_cla.v
module se_cla(
    input [26:0] a,           // 27位输入
    input [50:0] b,           // 51位输入
    output [50:0] sum         // 51位输出
);

    // 对27位输入a进行符号位扩展
    wire [50:0] a_ext;
    assign a_ext = {{24{a[26]}}, a};  // 符号位扩展
    
    // 低27位加法
    wire [26:0] sum_low;
    wire carry_out;
    
    add #(.width(27)) add_low(
        .a(a),
        .b(b[26:0]),
        .sus(1'b0),  // 无符号加法
        .sum({carry_out, sum_low})
    );
    
    // 高24位加法（考虑进位）
    wire [23:0] sum_high;
    
    s_cla s_cla_inst(
        .a(a_ext[50:27]),
        .b(b[50:27]),
        .cin(carry_out),
        .sum(sum_high)
    );
    
    // 拼接结果
    assign sum = {sum_high, sum_low};

endmodule

DCIM_Macro/rtl/accumulator.v
// 最终的、实例化se_cla的、电路稳定的累加器
module accumulator(
    input [26:0] a,
    input clk,
    input acm_en,
    input rstn,
    input st,
    output [50:0] nout
);

    // 内部累加寄存器
    reg [50:0] nout_1;
    
    // 模块输出直接来自寄存器
    assign nout = nout_1;

    // --- 用于计算的中间信号 ---
    wire [50:0] shifted_nout_1; // 用于存放 nout_1 << 1 的结果
    wire [50:0] sum_result;     // 加法器的输出

    // --- 组合逻辑部分 ---
    // 1. 对当前寄存器的值进行左移一位
    assign shifted_nout_1 = {nout_1[49:0], 1'b0};

    // 2. 实例化 se_cla 加法器来计算：(nout_1 << 1) + a
    se_cla se_cla_inst (
        .a(a),
        .b(shifted_nout_1),
        .sum(sum_result)
    );

    // --- 时序逻辑部分 ---
    // 在时钟边沿，用预先计算好的、稳定的加法结果来更新寄存器
    always @(posedge clk or negedge rstn) begin
        if (!rstn) begin
            nout_1 <= 51'b0;
        end else if (acm_en) begin
            if (st) begin
                nout_1 <= 51'b0;
            end else begin
                // 锁存稳定的加法结果
                nout_1 <= sum_result;
            end
        end
    end

endmodule

DCIM_Macro/rtl/global_io.v
module global_io(
    input [14:0] macout_a,    // MAC输出A
    input [14:0] macout_b,    // MAC输出B
    input clk,                // 时钟信号
    input acm_en,             // 累加器使能
    input rstn,               // 复位信号
    input st,                 // 累加器状态信号
    input wwidth,             // 权重位宽选择
    output [50:0] nout        // 最终输出
);

    // 内部信号
    wire [26:0] add_out;          // 27位加法器输出
    wire [26:0] adder_a_input;    // 加法器a端口的输入
    wire [26:0] adder_b_input;    // 加法器b端口的输入

    // 准备加法器的两个输入
    // adder_a_input 是零扩展后的 macout_a (低12位权重的结果)
    assign adder_a_input = {12'b0, macout_a};

    // adder_b_input 是移位后的 macout_b (高12位权重的结果, 仅在24b模式下有效)
    assign adder_b_input = wwidth ? {macout_b, 12'b0} : 27'b0;

    // 实例化一个27位的加法器
    add #(.width(27)) add_inst(
        .a(adder_a_input),
        .b(adder_b_input),
        .sus(1'b0),  // 无符号加法
        .sum(add_out)
    );
    
    // 扩展高位
    //assign add_out[26:16] = 11'b0;
    
    // 实例化累加器
    accumulator acc_inst(
        .a(add_out),
        .clk(clk),
        .acm_en(acm_en),
        .rstn(rstn),
        .st(st),
        .nout(nout)
    );

endmodule

DCIM_Macro/tb/tb_global_io.v
`timescale 1ns / 1ps

module tb_global_io;

    // Inputs
    reg [14:0] macout_a;
    reg [14:0] macout_b;
    reg clk;
    reg acm_en;
    reg rstn;
    reg st;
    reg wwidth;

    // Outputs
    wire [50:0] nout;

    // Instantiate the Unit Under Test (UUT)
    global_io uut (
        .macout_a(macout_a),
        .macout_b(macout_b),
        .clk(clk),
        .acm_en(acm_en),
        .rstn(rstn),
        .st(st),
        .wwidth(wwidth),
        .nout(nout)
    );

    // Clock generation
    initial begin
        clk = 0;
        forever #5 clk = ~clk;
    end

    initial begin
        // Initialize Inputs
        macout_a = 0;
        macout_b = 0;
        acm_en = 0;
        rstn = 0;
        st = 1;
        wwidth = 0;

        $dumpfile("tb_global_io.vcd");
        $dumpvars(0, tb_global_io);
        $monitor("Time=%0t rstn=%b st=%b acm_en=%b wwidth=%b macout_a=%d macout_b=%d | nout=%d", $time, rstn, st, acm_en, wwidth, macout_a, macout_b, nout);

        // Test Case 1: Reset
        $display("--- Test Case 1: Reset ---");
        #10;
        rstn = 1;
        #10;
        $display("Reset released. nout should be 0.");

        // Test Case 2: 12-bit weight mode (wwidth=0)
        $display("--- Test Case 2: 12-bit weight mode (wwidth=0) ---");
        st = 1; @(posedge clk); #1; // Reset accumulator
        st = 0;
        acm_en = 1;
        wwidth = 0; // macout_b is ignored
        macout_a = 10; macout_b = 999; @(posedge clk); #1; // nout = 10
        macout_a = 20; macout_b = 888; @(posedge clk); #1; // nout = (10<<1)+20 = 40
        macout_a = 30; macout_b = 777; @(posedge clk); #1; // nout = (40<<1)+30 = 110
        $display("12-bit mode accumulation finished. nout = %d", nout);

        // Test Case 3: 24-bit weight mode (wwidth=1)
        $display("--- Test Case 3: 24-bit weight mode (wwidth=1) ---");
        st = 1; // Reset accumulator
        @(posedge clk); #1;
        st = 0;
        wwidth = 1;
        // add_out = macout_a + (macout_b << 12)
        macout_a = 10; macout_b = 1; @(posedge clk); #1; // nout = 10 + (1<<12) = 4106
        $display("Cycle 1: nout = %d", nout);
        macout_a = 20; macout_b = 2; @(posedge clk); #1; // nout = (4106<<1) + (20 + (2<<12)) = 8212 + 8212 = 16424
        $display("Cycle 2: nout = %d", nout);

        // Test Case 4: acm_en disable/enable
        $display("--- Test Case 4: acm_en disable/enable ---");
        st = 1; @(posedge clk); #1; // Reset accumulator
        st = 0;
        wwidth = 0;
        acm_en = 1;
        macout_a = 100; @(posedge clk); #1; // nout = 100
        $display("acm_en=1, nout = %d", nout);
        acm_en = 0;
        macout_a = 50; @(posedge clk); #1; // nout should not change
        $display("acm_en=0, nout = %d (should be 100)", nout);
        acm_en = 1;
        macout_a = 5; @(posedge clk); #1; // nout = (100<<1) + 5 = 205
        $display("acm_en=1 again, nout = %d", nout);

        // Test Case 5: st during operation
        $display("--- Test Case 5: st during operation ---");
        st = 0;
        wwidth = 0;
        acm_en = 1;
        macout_a = 1; @(posedge clk); #1; // nout = (205<<1) + 1 = 411
        macout_a = 2; @(posedge clk); #1; // nout = (411<<1) + 2 = 824
        st = 1; // Reset accumulator
        @(posedge clk); #1;
        $display("st asserted, nout should be 0. nout = %d", nout);
        st = 0;
        macout_a = 99; @(posedge clk); #1; // nout = 99
        $display("st de-asserted, accumulation restarts. nout = %d", nout);

        #20;
        $finish;
    end

endmodule

DCIM_Macro/tb_global_io.vcd
$date
	Fri Aug 08 19:21:12 2025
$end
$version
	Icarus Verilog
$end
$timescale
	1ps
$end
$scope module tb_global_io $end
$var wire 51 ! nout [50:0] $end
$var reg 1 " acm_en $end
$var reg 1 # clk $end
$var reg 15 $ macout_a [14:0] $end
$var reg 15 % macout_b [14:0] $end
$var reg 1 & rstn $end
$var reg 1 ' st $end
$var reg 1 ( wwidth $end
$scope module uut $end
$var wire 1 " acm_en $end
$var wire 1 # clk $end
$var wire 15 ) macout_a [14:0] $end
$var wire 15 * macout_b [14:0] $end
$var wire 1 & rstn $end
$var wire 1 ' st $end
$var wire 1 ( wwidth $end
$var wire 51 + nout [50:0] $end
$var wire 27 , adder_b_input [26:0] $end
$var wire 27 - adder_a_input [26:0] $end
$var wire 27 . add_out [26:0] $end
$scope module acc_inst $end
$var wire 27 / a [26:0] $end
$var wire 1 " acm_en $end
$var wire 1 # clk $end
$var wire 51 0 nout [50:0] $end
$var wire 1 & rstn $end
$var wire 1 ' st $end
$var wire 51 1 sum_result [50:0] $end
$var wire 51 2 shifted_nout_1 [50:0] $end
$var reg 51 3 nout_1 [50:0] $end
$scope module se_cla_inst $end
$var wire 27 4 a [26:0] $end
$var wire 51 5 b [50:0] $end
$var wire 27 6 sum_low [26:0] $end
$var wire 24 7 sum_high [23:0] $end
$var wire 51 8 sum [50:0] $end
$var wire 1 9 carry_out $end
$var wire 51 : a_ext [50:0] $end
$scope module add_low $end
$var wire 27 ; a [26:0] $end
$var wire 28 < a_signed [27:0] $end
$var wire 27 = b [26:0] $end
$var wire 28 > b_signed [27:0] $end
$var wire 1 ? sus $end
$var wire 28 @ sum [27:0] $end
$var parameter 32 A width $end
$upscope $end
$scope module s_cla_inst $end
$var wire 24 B a [23:0] $end
$var wire 24 C b [23:0] $end
$var wire 1 9 cin $end
$var wire 24 D g [23:0] $end
$var wire 24 E p [23:0] $end
$var wire 24 F sum [23:0] $end
$var wire 7 G c_block [6:0] $end
$var wire 25 H c [24:0] $end
$var wire 6 I bp [5:0] $end
$var wire 6 J bg [5:0] $end
$upscope $end
$upscope $end
$upscope $end
$scope module add_inst $end
$var wire 27 K a [26:0] $end
$var wire 28 L a_signed [27:0] $end
$var wire 27 M b [26:0] $end
$var wire 28 N b_signed [27:0] $end
$var wire 1 O sus $end
$var wire 28 P sum [27:0] $end
$var parameter 32 Q width $end
$upscope $end
$upscope $end
$upscope $end
$enddefinitions $end
$comment Show the parameter values. $end
$dumpall
b11011 Q
b11011 A
$end
#0
$dumpvars
b0 P
0O
b0 N
b0 M
b0 L
b0 K
b0 J
b0 I
b0 H
b0 G
b0 F
b0 E
b0 D
b0 C
b0 B
b0 @
0?
b0 >
b0 =
b0 <
b0 ;
b0 :
09
b0 8
b0 7
b0 6
b0 5
b0 4
b0 3
b0 2
b0 1
b0 0
b0 /
b0 .
b0 -
b0 ,
b0 +
b0 *
b0 )
0(
1'
0&
b0 %
b0 $
0#
0"
b0 !
$end
#5000
1#
#10000
0#
1&
#15000
1#
#20000
0#
#25000
1#
#26000
b1010 1
b1010 8
b1010 6
b1010 :
b1010 @
b1010 <
b1010 .
b1010 /
b1010 4
b1010 ;
b1111100111 %
b1111100111 *
b1010 P
b1010 L
b1010 -
b1010 K
b1010 $
b1010 )
1"
0'
#30000
0#
#35000
b11110 1
b11110 8
b11110 6
b11110 @
b10100 >
b10100 =
b10100 2
b10100 5
b1010 !
b1010 +
b1010 0
b1010 3
1#
#36000
b101000 1
b101000 8
b101000 6
b10100 :
b101000 @
b10100 <
b10100 .
b10100 /
b10100 4
b10100 ;
b1101111000 %
b1101111000 *
b10100 P
b10100 L
b10100 -
b10100 K
b10100 $
b10100 )
#40000
0#
#45000
b1100100 1
b1100100 8
b1100100 6
b1100100 @
b1010000 >
b1010000 =
b1010000 2
b1010000 5
b101000 !
b101000 +
b101000 0
b101000 3
1#
#46000
b1101110 1
b1101110 8
b1101110 6
b11110 :
b1101110 @
b11110 <
b11110 .
b11110 /
b11110 4
b11110 ;
b1100001001 %
b1100001001 *
b11110 P
b11110 L
b11110 -
b11110 K
b11110 $
b11110 )
#50000
0#
#55000
b11111010 1
b11111010 8
b11111010 6
b11111010 @
b11011100 >
b11011100 =
b11011100 2
b11011100 5
b1101110 !
b1101110 +
b1101110 0
b1101110 3
1#
#56000
1'
#60000
0#
#65000
b11110 1
b11110 8
b11110 6
b11110 @
b0 >
b0 =
b0 2
b0 5
b0 !
b0 +
b0 0
b0 3
1#
#66000
b1000000001010 1
b1000000001010 8
b1000000001010 6
b1000000001010 :
b1000000001010 @
b1000000001010 <
b1000000001010 .
b1000000001010 /
b1000000001010 4
b1000000001010 ;
b1000000000000 N
b1000000000000 ,
b1000000000000 M
b1 %
b1 *
b1000000001010 P
b1010 L
b1010 -
b1010 K
b1010 $
b1010 )
1(
0'
#70000
0#
#75000
b11000000011110 1
b11000000011110 8
b11000000011110 6
b11000000011110 @
b10000000010100 >
b10000000010100 =
b10000000010100 2
b10000000010100 5
b1000000001010 !
b1000000001010 +
b1000000001010 0
b1000000001010 3
1#
#76000
b100000000101000 1
b100000000101000 8
b100000000101000 6
b10000000000000 N
b10000000000000 ,
b10000000000000 M
b10000000010100 :
b100000000101000 @
b10000000010100 <
b10000000010100 .
b10000000010100 /
b10000000010100 4
b10000000010100 ;
b10 %
b10 *
b10000000010100 P
b10100 L
b10100 -
b10100 K
b10100 $
b10100 )
#80000
0#
#85000
b1010000001100100 1
b1010000001100100 8
b1010000001100100 6
b1010000001100100 @
b1000000001010000 >
b1000000001010000 =
b1000000001010000 2
b1000000001010000 5
b100000000101000 !
b100000000101000 +
b100000000101000 0
b100000000101000 3
1#
#86000
1'
#90000
0#
#95000
b10000000010100 1
b10000000010100 8
b10000000010100 6
b10000000010100 @
b0 >
b0 =
b0 2
b0 5
b0 !
b0 +
b0 0
b0 3
1#
#96000
b1100100 1
b1100100 8
b1100100 6
b1100100 :
b1100100 @
b1100100 <
b1100100 .
b1100100 /
b1100100 4
b1100100 ;
b0 N
b0 ,
b0 M
b1100100 P
b1100100 L
b1100100 -
b1100100 K
b1100100 $
b1100100 )
0(
0'
#100000
0#
#105000
b100101100 1
b100101100 8
b100101100 6
b100101100 @
b11001000 >
b11001000 =
b11001000 2
b11001000 5
b1100100 !
b1100100 +
b1100100 0
b1100100 3
1#
#106000
b11111010 1
b11111010 8
b11111010 6
b110010 :
b11111010 @
b110010 <
b110010 .
b110010 /
b110010 4
b110010 ;
b110010 P
b110010 L
b110010 -
b110010 K
b110010 $
b110010 )
0"
#110000
0#
#115000
1#
#116000
b11001101 1
b11001101 8
b11001101 6
b101 :
b11001101 @
b101 <
b101 .
b101 /
b101 4
b101 ;
b101 P
b101 L
b101 -
b101 K
b101 $
b101 )
1"
#120000
0#
#125000
b110011111 1
b110011111 8
b110011111 6
b110011111 @
b110011010 >
b110011010 =
b110011010 2
b110011010 5
b11001101 !
b11001101 +
b11001101 0
b11001101 3
1#
#126000
b110011011 1
b110011011 8
b110011011 6
b1 :
b110011011 @
b1 <
b1 .
b1 /
b1 4
b1 ;
b1 P
b1 L
b1 -
b1 K
b1 $
b1 )
#130000
0#
#135000
b1100110111 1
b1100110111 8
b1100110111 6
b1100110111 @
b1100110110 >
b1100110110 =
b1100110110 2
b1100110110 5
b110011011 !
b110011011 +
b110011011 0
b110011011 3
1#
#136000
b1100111000 1
b1100111000 8
b1100111000 6
b10 :
b1100111000 @
b10 <
b10 .
b10 /
b10 4
b10 ;
b10 P
b10 L
b10 -
b10 K
b10 $
b10 )
#140000
0#
#145000
b11001110010 1
b11001110010 8
b11001110010 6
b11001110010 @
b11001110000 >
b11001110000 =
b11001110000 2
b11001110000 5
b1100111000 !
b1100111000 +
b1100111000 0
b1100111000 3
1#
#146000
1'
#150000
0#
#155000
b10 1
b10 8
b10 6
b10 @
b0 >
b0 =
b0 2
b0 5
b0 !
b0 +
b0 0
b0 3
1#
#156000
b1100011 1
b1100011 8
b1100011 6
b1100011 :
b1100011 @
b1100011 <
b1100011 .
b1100011 /
b1100011 4
b1100011 ;
b1100011 P
b1100011 L
b1100011 -
b1100011 K
b1100011 $
b1100011 )
0'
#160000
0#
#165000
b100101001 1
b100101001 8
b100101001 6
b100101001 @
b11000110 >
b11000110 =
b11000110 2
b11000110 5
b1100011 !
b1100011 +
b1100011 0
b1100011 3
1#
#170000
0#
#175000
b1010110101 1
b1010110101 8
b1010110101 6
b1010110101 @
b1001010010 >
b1001010010 =
b1001010010 2
b1001010010 5
b100101001 !
b100101001 +
b100101001 0
b100101001 3
1#
#180000
0#
#185000
b10111001101 1
b10111001101 8
b10111001101 6
b10111001101 @
b10101101010 >
b10101101010 =
b10101101010 2
b10101101010 5
b1010110101 !
b1010110101 +
b1010110101 0
b1010110101 3
1#
