DCIM_Macro/rtl/oai_mult.v
module oai_mult(
    input [11:0] a,           // 权重输入a
    input [11:0] b,           // 权重输入b
    input c,                  // 输入位c
    input d,                  // 输入位d
    output wire [11:0] e      // 乘法结果
);

    // OAI逻辑：e = ~((a | c) & (b | d))
    // 其中c和d是1位信号，需要扩展到12位
    wire [11:0] c_ext = {12{c}};  // 将c扩展到12位
    wire [11:0] d_ext = {12{d}};  // 将d扩展到12位
    
    // 实现OAI逻辑
    assign e = ~((a | c_ext) & (b | d_ext));

endmodule

DCIM_Macro/tb/tb_oai_mult.v
`timescale 1ns / 1ps

module tb_oai_mult;

    // Inputs
    reg [11:0] a;
    reg [11:0] b;
    reg c;
    reg d;

    // Outputs
    wire [11:0] e;

    // Instantiate the Unit Under Test (UUT)
    oai_mult uut (
        .a(a),
        .b(b),
        .c(c),
        .d(d),
        .e(e)
    );

    initial begin
        // Initialize Inputs
        a = 0;
        b = 0;
        c = 0;
        d = 0;

        $dumpfile("tb_oai_mult.vcd");
        $dumpvars(0, tb_oai_mult);

        // Test Case 1: c=0, d=0 => e = ~(a & b) (NAND)
        $display("--- Test Case 1: c=0, d=0 (NAND logic) ---");
        c = 0; d = 0;
        a = 12'hFFF; b = 12'hFFF; #10; $display("a=%h, b=%h, c=%b, d=%b => e=%h (expected 000)", a, b, c, d, e);
        a = 12'hFFF; b = 12'h000; #10; $display("a=%h, b=%h, c=%b, d=%b => e=%h (expected FFF)", a, b, c, d, e);
        a = 12'h000; b = 12'hFFF; #10; $display("a=%h, b=%h, c=%b, d=%b => e=%h (expected FFF)", a, b, c, d, e);
        a = 12'h000; b = 12'h000; #10; $display("a=%h, b=%h, c=%b, d=%b => e=%h (expected FFF)", a, b, c, d, e);
        a = 12'hF0F; b = 12'h0F0; #10; $display("a=%h, b=%h, c=%b, d=%b => e=%h (expected FFF)", a, b, c, d, e);
        a = 12'hA5A; b = 12'h5A5; #10; $display("a=%h, b=%h, c=%b, d=%b => e=%h (expected FFF)", a, b, c, d, e);

        // Test Case 2: c=0, d=1 => e = ~a (NOT a)
        $display("--- Test Case 2: c=0, d=1 (NOT a logic) ---");
        c = 0; d = 1;
        a = 12'hFFF; b = 12'hFFF; #10; $display("a=%h, b=%h, c=%b, d=%b => e=%h (expected 000)", a, b, c, d, e);
        a = 12'h000; b = 12'hFFF; #10; $display("a=%h, b=%h, c=%b, d=%b => e=%h (expected FFF)", a, b, c, d, e);
        a = 12'hF0F; b = 12'hFFF; #10; $display("a=%h, b=%h, c=%b, d=%b => e=%h (expected 0F0)", a, b, c, d, e);
        a = 12'hA5A; b = 12'hFFF; #10; $display("a=%h, b=%h, c=%b, d=%b => e=%h (expected 5A5)", a, b, c, d, e);

        // Test Case 3: c=1, d=0 => e = ~b (NOT b)
        $display("--- Test Case 3: c=1, d=0 (NOT b logic) ---");
        c = 1; d = 0;
        a = 12'hFFF; b = 12'hFFF; #10; $display("a=%h, b=%h, c=%b, d=%b => e=%h (expected 000)", a, b, c, d, e);
        a = 12'hFFF; b = 12'h000; #10; $display("a=%h, b=%h, c=%b, d=%b => e=%h (expected FFF)", a, b, c, d, e);
        a = 12'hFFF; b = 12'hF0F; #10; $display("a=%h, b=%h, c=%b, d=%b => e=%h (expected 0F0)", a, b, c, d, e);
        a = 12'hFFF; b = 12'hA5A; #10; $display("a=%h, b=%h, c=%b, d=%b => e=%h (expected 5A5)", a, b, c, d, e);

        // Test Case 4: c=1, d=1 => e = 0
        $display("--- Test Case 4: c=1, d=1 (Output is always 0) ---");
        c = 1; d = 1;
        a = 12'hFFF; b = 12'hFFF; #10; $display("a=%h, b=%h, c=%b, d=%b => e=%h (expected 000)", a, b, c, d, e);
        a = 12'h000; b = 12'h000; #10; $display("a=%h, b=%h, c=%b, d=%b => e=%h (expected 000)", a, b, c, d, e);
        a = 12'hA5A; b = 12'h5A5; #10; $display("a=%h, b=%h, c=%b, d=%b => e=%h (expected 000)", a, b, c, d, e);

        // Test Case 5: Random values
        $display("--- Test Case 5: Random values ---");
        repeat(5) begin
            a = $random;
            b = $random;
            c = $random;
            d = $random;
            #10;
            $display("a=%h, b=%h, c=%b, d=%b => e=%h (expected %h)", a, b, c, d, e, ~((a|c)&(b|d)));
        end

        #20;
        $finish;
    end

endmodule

DCIM_Macro/tb_oai_mult.vcd
$date
	Fri Aug 08 19:20:51 2025
$end
$version
	Icarus Verilog
$end
$timescale
	1ps
$end
$scope module tb_oai_mult $end
$var wire 12 ! e [11:0] $end
$var reg 12 " a [11:0] $end
$var reg 12 # b [11:0] $end
$var reg 1 $ c $end
$var reg 1 % d $end
$scope module uut $end
$var wire 12 & a [11:0] $end
$var wire 12 ' b [11:0] $end
$var wire 1 $ c $end
$var wire 1 % d $end
$var wire 12 ( e [11:0] $end
$var wire 12 ) d_ext [11:0] $end
$var wire 12 * c_ext [11:0] $end
$upscope $end
$upscope $end
$enddefinitions $end
$comment Show the parameter values. $end
$dumpall
$end
#0
$dumpvars
b0 *
b0 )
b0 (
b111111111111 '
b111111111111 &
0%
0$
b111111111111 #
b111111111111 "
b0 !
$end
#10000
b111111111111 !
b111111111111 (
b0 #
b0 '
#20000
b111111111111 #
b111111111111 '
b0 "
b0 &
#30000
b0 #
b0 '
#40000
b11110000 #
b11110000 '
b111100001111 "
b111100001111 &
#50000
b10110100101 #
b10110100101 '
b101001011010 "
b101001011010 &
#60000
b0 !
b0 (
b111111111111 #
b111111111111 '
b111111111111 "
b111111111111 &
b111111111111 )
1%
#70000
b111111111111 !
b111111111111 (
b0 "
b0 &
#80000
b11110000 !
b11110000 (
b111100001111 "
b111100001111 &
#90000
b10110100101 !
b10110100101 (
b101001011010 "
b101001011010 &
#100000
b0 !
b0 (
b111111111111 "
b111111111111 &
b0 )
0%
b111111111111 *
1$
#110000
b111111111111 !
b111111111111 (
b0 #
b0 '
#120000
b11110000 !
b11110000 (
b111100001111 #
b111100001111 '
#130000
b10110100101 !
b10110100101 (
b101001011010 #
b101001011010 '
#140000
b0 !
b0 (
b111111111111 #
b111111111111 '
b111111111111 )
1%
#150000
b0 #
b0 '
b0 "
b0 &
#160000
b10110100101 #
b10110100101 '
b101001011010 "
b101001011010 &
#170000
b111010000001 #
b111010000001 '
b10100100100 "
b10100100100 &
#180000
b11001110010 !
b11001110010 (
b0 )
0%
b100110001101 #
b100110001101 '
b101100001101 "
b101100001101 &
#190000
b110011111110 !
b110011111110 (
b111111111111 )
1%
b0 *
0$
b110100001101 #
b110100001101 '
b1100000001 "
b1100000001 &
#200000
b100001110011 !
b100001110011 (
b0 )
0%
b111111111111 *
1$
b11110001100 #
b11110001100 '
b11111101101 "
b11111101101 &
#210000
b0 !
b0 (
b111111111111 )
1%
b1010101010 #
b1010101010 '
b10011000101 "
b10011000101 &
