DCIM_Macro/rtl/rwldrv.v
module rwldrv(
    input [191:0] xin0,       // 输入数据向量
    input [5:0] sel,          // 选择信号
    input cima,               // 片选信号
    input inwidth,            // 新增：输入位宽选择
    output reg [7:0] rwlb_row0, // 行驱动信号0
    output reg [7:0] rwlb_row1  // 行驱动信号1
);

    always @(*) begin : RWLDRV_LOGIC
        reg [7:0] selected_bits;
        integer i;
        reg [5:0] bit_to_select;

        // 根据sel和inwidth计算出从MSB开始的正确位索引
        if (inwidth) begin // 24-bit 模式
            bit_to_select = 23 - sel;
        end else begin // 12-bit 模式
            bit_to_select = 11 - sel;
        end

        // 遍历8个数据项
        for (i = 0; i < 8; i = i + 1) begin
            // 从第i个24-bit数据中，提取出正确的位
            selected_bits[i] = xin0[(i*24) + bit_to_select];
        end

        // 根据cima信号，将取反后的结果送到正确的bank，并屏蔽另一个
        if (cima == 1'b0) begin
            // 选择bank0，激活rwlb_row0，屏蔽rwlb_row1
            rwlb_row0 = ~selected_bits;
            rwlb_row1 = 8'hFF; // 强制为全1以屏蔽
        end else begin
            // 选择bank1，屏蔽rwlb_row0，激活rwlb_row1
            rwlb_row0 = 8'hFF; // 强制为全1以屏蔽
            rwlb_row1 = ~selected_bits;
        end
    end

endmodule

DCIM_Macro/tb_verify/tb_verify_rwldrv.v
`timescale 1ns / 1ps

module tb_verify_rwldrv;

    // Inputs
    reg [191:0] xin0;
    reg [5:0] sel;
    reg cima;
    reg inwidth;

    // Outputs
    wire [7:0] rwlb_row0;
    wire [7:0] rwlb_row1;

    // Instantiate the Unit Under Test (UUT)
    rwldrv uut (
        .xin0(xin0),
        .sel(sel),
        .cima(cima),
        .inwidth(inwidth),
        .rwlb_row0(rwlb_row0),
        .rwlb_row1(rwlb_row1)
    );

    integer i;
    integer errors = 0;

    // Verification task
    task check_output;
        input [7:0] expected_row0;
        input [7:0] expected_row1;
        begin
            #1; // Settle time
            if (rwlb_row0 !== expected_row0 || rwlb_row1 !== expected_row1) begin
                $display("ERROR @ Time=%0t: sel=%d, cima=%b, inwidth=%b", $time, sel, cima, inwidth);
                $display("  rwlb_row0 = %h (expected %h)", rwlb_row0, expected_row0);
                $display("  rwlb_row1 = %h (expected %h)", rwlb_row1, expected_row1);
                errors = errors + 1;
            end
        end
    endtask

    initial begin
        // Initialize Inputs
        xin0 = 0;
        sel = 0;
        cima = 0;
        inwidth = 0;

        // Setup xin0 with the same pattern as the original tb
        for (i=0; i<8; i=i+1) begin
            xin0[i*24 +: 24] = 24'hAAAAAA + i;
        end
        #10;

        $dumpfile("tb_verify_rwldrv.vcd");
        $dumpvars(0, tb_verify_rwldrv);

        $display("--- Verification for rwldrv starting ---");

        // Test Case 1: 12-bit mode, bank 0
        $display("// Test Case 1: 12-bit mode, bank 0");
        inwidth = 0;
        cima = 0;
        for (sel = 0; sel < 12; sel = sel + 1) begin
            #10;
            case (sel)
                0: check_output(8'h00, 8'hff);
                1: check_output(8'hff, 8'hff);
                2: check_output(8'h00, 8'hff);
                3: check_output(8'hff, 8'hff);
                4: check_output(8'h00, 8'hff);
                5: check_output(8'hff, 8'hff);
                6: check_output(8'h00, 8'hff);
                7: check_output(8'h3f, 8'hff);
                8: check_output(8'hc0, 8'hff);
                9: check_output(8'hc3, 8'hff);
                10: check_output(8'hcc, 8'hff);
                11: check_output(8'h55, 8'hff);
            endcase
        end

        // Test Case 2: 12-bit mode, bank 1
        $display("// Test Case 2: 12-bit mode, bank 1");
        inwidth = 0;
        cima = 1;
        for (sel = 0; sel < 12; sel = sel + 1) begin
            #10;
            case (sel)
                0: check_output(8'hff, 8'h00);
                1: check_output(8'hff, 8'hff);
                2: check_output(8'hff, 8'h00);
                3: check_output(8'hff, 8'hff);
                4: check_output(8'hff, 8'h00);
                5: check_output(8'hff, 8'hff);
                6: check_output(8'hff, 8'h00);
                7: check_output(8'hff, 8'h3f);
                8: check_output(8'hff, 8'hc0);
                9: check_output(8'hff, 8'hc3);
                10: check_output(8'hff, 8'hcc);
                11: check_output(8'hff, 8'h55);
            endcase
        end

        // Test Case 3: 24-bit mode, bank 0
        $display("// Test Case 3: 24-bit mode, bank 0");
        inwidth = 1;
        cima = 0;
        for (sel = 0; sel < 24; sel = sel + 1) begin
            #10;
            case (sel)
                0: check_output(8'h00, 8'hff);
                1: check_output(8'hff, 8'hff);
                2: check_output(8'h00, 8'hff);
                3: check_output(8'hff, 8'hff);
                4: check_output(8'h00, 8'hff);
                5: check_output(8'hff, 8'hff);
                6: check_output(8'h00, 8'hff);
                7: check_output(8'hff, 8'hff);
                8: check_output(8'h00, 8'hff);
                9: check_output(8'hff, 8'hff);
                10: check_output(8'h00, 8'hff);
                11: check_output(8'hff, 8'hff);
                12: check_output(8'h00, 8'hff);
                13: check_output(8'hff, 8'hff);
                14: check_output(8'h00, 8'hff);
                15: check_output(8'hff, 8'hff);
                16: check_output(8'h00, 8'hff);
                17: check_output(8'hff, 8'hff);
                18: check_output(8'h00, 8'hff);
                19: check_output(8'h3f, 8'hff);
                20: check_output(8'hc0, 8'hff);
                21: check_output(8'hc3, 8'hff);
                22: check_output(8'hcc, 8'hff);
                23: check_output(8'h55, 8'hff);
            endcase
        end

        // Test Case 4: 24-bit mode, bank 1
        $display("// Test Case 4: 24-bit mode, bank 1");
        inwidth = 1;
        cima = 1;
        for (sel = 0; sel < 24; sel = sel + 1) begin
            #10;
            case (sel)
                0: check_output(8'hff, 8'h00);
                1: check_output(8'hff, 8'hff);
                2: check_output(8'hff, 8'h00);
                3: check_output(8'hff, 8'hff);
                4: check_output(8'hff, 8'h00);
                5: check_output(8'hff, 8'hff);
                6: check_output(8'hff, 8'h00);
                7: check_output(8'hff, 8'hff);
                8: check_output(8'hff, 8'h00);
                9: check_output(8'hff, 8'hff);
                10: check_output(8'hff, 8'h00);
                11: check_output(8'hff, 8'hff);
                12: check_output(8'hff, 8'h00);
                13: check_output(8'hff, 8'hff);
                14: check_output(8'hff, 8'h00);
                15: check_output(8'hff, 8'hff);
                16: check_output(8'hff, 8'h00);
                17: check_output(8'hff, 8'hff);
                18: check_output(8'hff, 8'h00);
                19: check_output(8'hff, 8'h3f);
                20: check_output(8'hff, 8'hc0);
                21: check_output(8'hff, 8'hc3);
                22: check_output(8'hff, 8'hcc);
                23: check_output(8'hff, 8'h55);
            endcase
        end

        #20;
        if (errors == 0) begin
            $display("--- All rwldrv checks PASSED ---");
        end else begin
            $display("--- rwldrv verification FAILED with %0d errors ---", errors);
        end
        $finish;
    end

endmodule

DCIM_Macro/tb_verify_rwldrv.vcd
$date
	Sat Aug 09 02:11:30 2025
$end
$version
	Icarus Verilog
$end
$timescale
	1ps
$end
$scope module tb_verify_rwldrv $end
$var wire 8 ! rwlb_row1 [7:0] $end
$var wire 8 " rwlb_row0 [7:0] $end
$var reg 1 # cima $end
$var reg 1 $ inwidth $end
$var reg 6 % sel [5:0] $end
$var reg 192 & xin0 [191:0] $end
$var integer 32 ' errors [31:0] $end
$var integer 32 ( i [31:0] $end
$scope module uut $end
$var wire 1 # cima $end
$var wire 1 $ inwidth $end
$var wire 6 ) sel [5:0] $end
$var wire 192 * xin0 [191:0] $end
$var reg 8 + rwlb_row0 [7:0] $end
$var reg 8 , rwlb_row1 [7:0] $end
$scope begin RWLDRV_LOGIC $end
$var reg 6 - bit_to_select [5:0] $end
$var reg 8 . selected_bits [7:0] $end
$var integer 32 / i [31:0] $end
$upscope $end
$upscope $end
$scope task check_output $end
$var reg 8 0 expected_row0 [7:0] $end
$var reg 8 1 expected_row1 [7:0] $end
$upscope $end
$upscope $end
$enddefinitions $end
$comment Show the parameter values. $end
$dumpall
$end
#10000
$dumpvars
bx 1
bx 0
b1000 /
b11111111 .
b1011 -
b11111111 ,
b0 +
b101010101010101010110001101010101010101010110000101010101010101010101111101010101010101010101110101010101010101010101101101010101010101010101100101010101010101010101011101010101010101010101010 *
b0 )
b1000 (
b0 '
b101010101010101010110001101010101010101010110000101010101010101010101111101010101010101010101110101010101010101010101101101010101010101010101100101010101010101010101011101010101010101010101010 &
b0 %
0$
0#
b0 "
b11111111 !
$end
#20000
b11111111 1
b0 0
#21000
b11111111 "
b11111111 +
b0 .
b1000 /
b1010 -
b1 %
b1 )
#31000
b11111111 0
#32000
b0 "
b0 +
b11111111 .
b1000 /
b1001 -
b10 %
b10 )
#42000
b0 0
#43000
b11111111 "
b11111111 +
b0 .
b1000 /
b1000 -
b11 %
b11 )
#53000
b11111111 0
#54000
b0 "
b0 +
b11111111 .
b1000 /
b111 -
b100 %
b100 )
#64000
b0 0
#65000
b11111111 "
b11111111 +
b0 .
b1000 /
b110 -
b101 %
b101 )
#75000
b11111111 0
#76000
b0 "
b0 +
b11111111 .
b1000 /
b101 -
b110 %
b110 )
#86000
b0 0
#87000
b111111 "
b111111 +
b11000000 .
b1000 /
b100 -
b111 %
b111 )
#97000
b111111 0
#98000
b11000000 "
b11000000 +
b111111 .
b1000 /
b11 -
b1000 %
b1000 )
#108000
b11000000 0
#109000
b11000011 "
b11000011 +
b111100 .
b1000 /
b10 -
b1001 %
b1001 )
#119000
b11000011 0
#120000
b11001100 "
b11001100 +
b110011 .
b1000 /
b1 -
b1010 %
b1010 )
#130000
b11001100 0
#131000
b1010101 "
b1010101 +
b10101010 .
b1000 /
b0 -
b1011 %
b1011 )
#141000
b1010101 0
#142000
b0 !
b0 ,
b11111111 "
b11111111 +
b11111111 .
b1000 /
b1011 -
1#
b0 %
b0 )
#152000
b0 1
b11111111 0
#153000
b11111111 !
b11111111 ,
b0 .
b1000 /
b1010 -
b1 %
b1 )
#163000
b11111111 1
#164000
b0 !
b0 ,
b11111111 .
b1000 /
b1001 -
b10 %
b10 )
#174000
b0 1
#175000
b11111111 !
b11111111 ,
b0 .
b1000 /
b1000 -
b11 %
b11 )
#185000
b11111111 1
#186000
b0 !
b0 ,
b11111111 .
b1000 /
b111 -
b100 %
b100 )
#196000
b0 1
#197000
b11111111 !
b11111111 ,
b0 .
b1000 /
b110 -
b101 %
b101 )
#207000
b11111111 1
#208000
b0 !
b0 ,
b11111111 .
b1000 /
b101 -
b110 %
b110 )
#218000
b0 1
#219000
b111111 !
b111111 ,
b11000000 .
b1000 /
b100 -
b111 %
b111 )
#229000
b111111 1
#230000
b11000000 !
b11000000 ,
b111111 .
b1000 /
b11 -
b1000 %
b1000 )
#240000
b11000000 1
#241000
b11000011 !
b11000011 ,
b111100 .
b1000 /
b10 -
b1001 %
b1001 )
#251000
b11000011 1
#252000
b11001100 !
b11001100 ,
b110011 .
b1000 /
b1 -
b1010 %
b1010 )
#262000
b11001100 1
#263000
b1010101 !
b1010101 ,
b10101010 .
b1000 /
b0 -
b1011 %
b1011 )
#273000
b1010101 1
#274000
b11111111 !
b11111111 ,
b0 "
b0 +
b11111111 .
b1000 /
b10111 -
0#
1$
b0 %
b0 )
#284000
b11111111 1
b0 0
#285000
b11111111 "
b11111111 +
b0 .
b1000 /
b10110 -
b1 %
b1 )
#295000
b11111111 0
#296000
b0 "
b0 +
b11111111 .
b1000 /
b10101 -
b10 %
b10 )
#306000
b0 0
#307000
b11111111 "
b11111111 +
b0 .
b1000 /
b10100 -
b11 %
b11 )
#317000
b11111111 0
#318000
b0 "
b0 +
b11111111 .
b1000 /
b10011 -
b100 %
b100 )
#328000
b0 0
#329000
b11111111 "
b11111111 +
b0 .
b1000 /
b10010 -
b101 %
b101 )
#339000
b11111111 0
#340000
b0 "
b0 +
b11111111 .
b1000 /
b10001 -
b110 %
b110 )
#350000
b0 0
#351000
b11111111 "
b11111111 +
b0 .
b1000 /
b10000 -
b111 %
b111 )
#361000
b11111111 0
#362000
b0 "
b0 +
b11111111 .
b1000 /
b1111 -
b1000 %
b1000 )
#372000
b0 0
#373000
b11111111 "
b11111111 +
b0 .
b1000 /
b1110 -
b1001 %
b1001 )
#383000
b11111111 0
#384000
b0 "
b0 +
b11111111 .
b1000 /
b1101 -
b1010 %
b1010 )
#394000
b0 0
#395000
b11111111 "
b11111111 +
b0 .
b1000 /
b1100 -
b1011 %
b1011 )
#405000
b11111111 0
#406000
b0 "
b0 +
b11111111 .
b1000 /
b1011 -
b1100 %
b1100 )
#416000
b0 0
#417000
b11111111 "
b11111111 +
b0 .
b1000 /
b1010 -
b1101 %
b1101 )
#427000
b11111111 0
#428000
b0 "
b0 +
b11111111 .
b1000 /
b1001 -
b1110 %
b1110 )
#438000
b0 0
#439000
b11111111 "
b11111111 +
b0 .
b1000 /
b1000 -
b1111 %
b1111 )
#449000
b11111111 0
#450000
b0 "
b0 +
b11111111 .
b1000 /
b111 -
b10000 %
b10000 )
#460000
b0 0
#461000
b11111111 "
b11111111 +
b0 .
b1000 /
b110 -
b10001 %
b10001 )
#471000
b11111111 0
#472000
b0 "
b0 +
b11111111 .
b1000 /
b101 -
b10010 %
b10010 )
#482000
b0 0
#483000
b111111 "
b111111 +
b11000000 .
b1000 /
b100 -
b10011 %
b10011 )
#493000
b111111 0
#494000
b11000000 "
b11000000 +
b111111 .
b1000 /
b11 -
b10100 %
b10100 )
#504000
b11000000 0
#505000
b11000011 "
b11000011 +
b111100 .
b1000 /
b10 -
b10101 %
b10101 )
#515000
b11000011 0
#516000
b11001100 "
b11001100 +
b110011 .
b1000 /
b1 -
b10110 %
b10110 )
#526000
b11001100 0
#527000
b1010101 "
b1010101 +
b10101010 .
b1000 /
b0 -
b10111 %
b10111 )
#537000
b1010101 0
#538000
b0 !
b0 ,
b11111111 "
b11111111 +
b11111111 .
b1000 /
b10111 -
1#
b0 %
b0 )
#548000
b0 1
b11111111 0
#549000
b11111111 !
b11111111 ,
b0 .
b1000 /
b10110 -
b1 %
b1 )
#559000
b11111111 1
#560000
b0 !
b0 ,
b11111111 .
b1000 /
b10101 -
b10 %
b10 )
#570000
b0 1
#571000
b11111111 !
b11111111 ,
b0 .
b1000 /
b10100 -
b11 %
b11 )
#581000
b11111111 1
#582000
b0 !
b0 ,
b11111111 .
b1000 /
b10011 -
b100 %
b100 )
#592000
b0 1
#593000
b11111111 !
b11111111 ,
b0 .
b1000 /
b10010 -
b101 %
b101 )
#603000
b11111111 1
#604000
b0 !
b0 ,
b11111111 .
b1000 /
b10001 -
b110 %
b110 )
#614000
b0 1
#615000
b11111111 !
b11111111 ,
b0 .
b1000 /
b10000 -
b111 %
b111 )
#625000
b11111111 1
#626000
b0 !
b0 ,
b11111111 .
b1000 /
b1111 -
b1000 %
b1000 )
#636000
b0 1
#637000
b11111111 !
b11111111 ,
b0 .
b1000 /
b1110 -
b1001 %
b1001 )
#647000
b11111111 1
#648000
b0 !
b0 ,
b11111111 .
b1000 /
b1101 -
b1010 %
b1010 )
#658000
b0 1
#659000
b11111111 !
b11111111 ,
b0 .
b1000 /
b1100 -
b1011 %
b1011 )
#669000
b11111111 1
#670000
b0 !
b0 ,
b11111111 .
b1000 /
b1011 -
b1100 %
b1100 )
#680000
b0 1
#681000
b11111111 !
b11111111 ,
b0 .
b1000 /
b1010 -
b1101 %
b1101 )
#691000
b11111111 1
#692000
b0 !
b0 ,
b11111111 .
b1000 /
b1001 -
b1110 %
b1110 )
#702000
b0 1
#703000
b11111111 !
b11111111 ,
b0 .
b1000 /
b1000 -
b1111 %
b1111 )
#713000
b11111111 1
#714000
b0 !
b0 ,
b11111111 .
b1000 /
b111 -
b10000 %
b10000 )
#724000
b0 1
#725000
b11111111 !
b11111111 ,
b0 .
b1000 /
b110 -
b10001 %
b10001 )
#735000
b11111111 1
#736000
b0 !
b0 ,
b11111111 .
b1000 /
b101 -
b10010 %
b10010 )
#746000
b0 1
#747000
b111111 !
b111111 ,
b11000000 .
b1000 /
b100 -
b10011 %
b10011 )
#757000
b111111 1
#758000
b11000000 !
b11000000 ,
b111111 .
b1000 /
b11 -
b10100 %
b10100 )
#768000
b11000000 1
#769000
b11000011 !
b11000011 ,
b111100 .
b1000 /
b10 -
b10101 %
b10101 )
#779000
b11000011 1
#780000
b11001100 !
b11001100 ,
b110011 .
b1000 /
b1 -
b10110 %
b10110 )
#790000
b11001100 1
#791000
b1010101 !
b1010101 ,
b10101010 .
b1000 /
b0 -
b10111 %
b10111 )
#801000
b1010101 1
#802000
bx000000 !
bx000000 ,
bx111111 .
b1000 /
b111111 -
b11000 %
b11000 )
