DCIM_Macro/rtl/cim_bank.v
module cim_bank(
    input [23:0] D,           // 写入数据
    input [7:0] WA,           // 写地址 (one-hot编码)
    output [95:0] wb_a,       // 权重输出A
    output [95:0] wb_b        // 权重输出B
);

    // 8x24-bit存储器数组
    reg [23:0] mem [7:0];

    // Initialize memory
    integer i;
    initial begin
        for (i = 0; i < 8; i = i + 1) begin
            mem[i] = 0;
        end
    end

    // 写操作 - 根据one-hot地址写入数据
    always @(*) begin
        case (WA)
            8'b00000001: mem[0] = D;
            8'b00000010: mem[1] = D;
            8'b00000100: mem[2] = D;
            8'b00001000: mem[3] = D;
            8'b00010000: mem[4] = D;
            8'b00100000: mem[5] = D;
            8'b01000000: mem[6] = D;
            8'b10000000: mem[7] = D;
            default: ; // 无操作
        endcase
    end

    // 读操作 - 持续输出所有存储单元内容的反相值，以实现AND逻辑
    // 将每个24-bit存储单元的低12位拼接并取反，作为 wb_a
    assign wb_a = ~{mem[7][11:0], mem[6][11:0], mem[5][11:0], mem[4][11:0],
                    mem[3][11:0], mem[2][11:0], mem[1][11:0], mem[0][11:0]};

    // 将每个24-bit存储单元的高12位拼接并取反，作为 wb_b
    assign wb_b = ~{mem[7][23:12], mem[6][23:12], mem[5][23:12], mem[4][23:12],
                    mem[3][23:12], mem[2][23:12], mem[1][23:12], mem[0][23:12]};

endmodule

DCIM_Macro/tb_verify/tb_verify_cim_bank.v
`timescale 1ns / 1ps

module tb_verify_cim_bank;

    // Inputs
    reg [23:0] D;
    reg [7:0] WA;

    // Outputs
    wire [95:0] wb_a;
    wire [95:0] wb_b;

    // Instantiate the Unit Under Test (UUT)
    cim_bank uut (
        .D(D),
        .WA(WA),
        .wb_a(wb_a),
        .wb_b(wb_b)
    );

    integer i;
    integer errors = 0;

    // Verification task
    task check_output;
        input [95:0] expected_wb_a;
        input [95:0] expected_wb_b;
        begin
            #1; // Allow for combinational logic to settle
            if (wb_a !== expected_wb_a || wb_b !== expected_wb_b) begin
                $display("ERROR @ Time=%0t: WA=%h", $time, WA);
                $display("  wb_a = %h (expected %h)", wb_a, expected_wb_a);
                $display("  wb_b = %h (expected %h)", wb_b, expected_wb_b);
                errors = errors + 1;
            end
        end
    endtask

    initial begin
        // Initialize Inputs
        D = 0;
        WA = 0;

        $dumpfile("tb_verify_cim_bank.vcd");
        $dumpvars(0, tb_verify_cim_bank);
        #1;

        // --- Test Case 1: Write to all memory locations ---
        $display("--- Test Case 1: Write to all memory locations ---");
        for (i = 0; i < 8; i = i + 1) begin
            WA = 1 << i;
            D = {12'h100 + i, 12'hA00 + i};
            #10;
            case (i)
                0: check_output(96'hfffffffffffffffffffff5ff, 96'hffffffffffffffffffffffff);
                1: check_output(96'hffffffffffffffffff5fe5ff, 96'hffffffffffffffffffffffff);
                2: check_output(96'hfffffffffffffff5fd5fe5ff, 96'hffffffffffffffffffffffff);
                3: check_output(96'hffffffffffff5fc5fd5fe5ff, 96'hffffffffffffffffffffffff);
                4: check_output(96'hfffffffff5fb5fc5fd5fe5ff, 96'hffffffffffffffffffffffff);
                5: check_output(96'hffffff5fa5fb5fc5fd5fe5ff, 96'hffffffffffffffffffffffff);
                6: check_output(96'hfff5f95fa5fb5fc5fd5fe5ff, 96'hffffffffffffffffffffffff);
                7: check_output(96'h5f85f95fa5fb5fc5fd5fe5ff, 96'hffffffffffffffffffffffff);
            endcase
        end
        WA = 8'b0;
        #10;
        check_output(96'h5f85f95fa5fb5fc5fd5fe5ff, 96'hffffffffffffffffffffffff);

        // --- Test Case 2: Overwrite location 4 ---
        $display("--- Test Case 2: Overwrite location 4 ---");
        WA = 1 << 4;
        D = 24'hDEADBE;
        #10;
        check_output(96'h5f85f95fa2415fc5fd5fe5ff, 96'hfffffffff215ffffffffffff);
        WA = 8'b0;
        #10;
        check_output(96'h5f85f95fa2415fc5fd5fe5ff, 96'hfffffffff215ffffffffffff);

        // --- Test Case 3: Write with WA=0 (should be no-op) ---
        $display("--- Test Case 3: Write with WA=0 (should be no-op) ---");
        WA = 8'b0;
        D = 24'hFFFFFF;
        #10;
        check_output(96'h5f85f95fa2415fc5fd5fe5ff, 96'hfffffffff215ffffffffffff);

        // Final result
        #20;
        if (errors == 0)
            $display("--- VERIFICATION PASSED ---");
        else
            $display("--- VERIFICATION FAILED: %0d errors ---", errors);

        $finish;
    end

endmodule

DCIM_Macro/tb_verify_cim_bank.vcd
$date
	Sat Aug 09 02:11:24 2025
$end
$version
	Icarus Verilog
$end
$timescale
	1ps
$end
$scope module tb_verify_cim_bank $end
$var wire 96 ! wb_b [95:0] $end
$var wire 96 " wb_a [95:0] $end
$var reg 24 # D [23:0] $end
$var reg 8 $ WA [7:0] $end
$var integer 32 % errors [31:0] $end
$var integer 32 & i [31:0] $end
$scope module uut $end
$var wire 24 ' D [23:0] $end
$var wire 8 ( WA [7:0] $end
$var wire 96 ) wb_a [95:0] $end
$var wire 96 * wb_b [95:0] $end
$var integer 32 + i [31:0] $end
$upscope $end
$scope task check_output $end
$var reg 96 , expected_wb_a [95:0] $end
$var reg 96 - expected_wb_b [95:0] $end
$upscope $end
$upscope $end
$enddefinitions $end
$comment Show the parameter values. $end
$dumpall
$end
#0
$dumpvars
bx -
bx ,
b1000 +
b111111111111111111111111111111111111111111111111111111111111111111111111111111111111111111111111 *
b111111111111111111111111111111111111111111111111111111111111111111111111111111111111111111111111 )
b0 (
b0 '
bx &
b0 %
b0 $
b0 #
b111111111111111111111111111111111111111111111111111111111111111111111111111111111111111111111111 "
b111111111111111111111111111111111111111111111111111111111111111111111111111111111111111111111111 !
$end
#1000
b111111111111111111111111111111111111111111111111111111111111111111111111111111111111010111111111 "
b111111111111111111111111111111111111111111111111111111111111111111111111111111111111010111111111 )
b101000000000 #
b101000000000 '
b1 $
b1 (
b0 &
#11000
b111111111111111111111111111111111111111111111111111111111111111111111111111111111111111111111111 -
b111111111111111111111111111111111111111111111111111111111111111111111111111111111111010111111111 ,
#12000
b111111111111111111111111111111111111111111111111111111111111111111111111010111111110010111111111 "
b111111111111111111111111111111111111111111111111111111111111111111111111010111111110010111111111 )
b101000000001 #
b101000000001 '
b10 $
b10 (
b1 &
#22000
b111111111111111111111111111111111111111111111111111111111111111111111111010111111110010111111111 ,
#23000
b111111111111111111111111111111111111111111111111111111111111010111111101010111111110010111111111 "
b111111111111111111111111111111111111111111111111111111111111010111111101010111111110010111111111 )
b101000000010 #
b101000000010 '
b100 $
b100 (
b10 &
#33000
b111111111111111111111111111111111111111111111111111111111111010111111101010111111110010111111111 ,
#34000
b111111111111111111111111111111111111111111111111010111111100010111111101010111111110010111111111 "
b111111111111111111111111111111111111111111111111010111111100010111111101010111111110010111111111 )
b101000000011 #
b101000000011 '
b1000 $
b1000 (
b11 &
#44000
b111111111111111111111111111111111111111111111111010111111100010111111101010111111110010111111111 ,
#45000
b111111111111111111111111111111111111010111111011010111111100010111111101010111111110010111111111 "
b111111111111111111111111111111111111010111111011010111111100010111111101010111111110010111111111 )
b101000000100 #
b101000000100 '
b10000 $
b10000 (
b100 &
#55000
b111111111111111111111111111111111111010111111011010111111100010111111101010111111110010111111111 ,
#56000
b111111111111111111111111010111111010010111111011010111111100010111111101010111111110010111111111 "
b111111111111111111111111010111111010010111111011010111111100010111111101010111111110010111111111 )
b101000000101 #
b101000000101 '
b100000 $
b100000 (
b101 &
#66000
b111111111111111111111111010111111010010111111011010111111100010111111101010111111110010111111111 ,
#67000
b111111111111010111111001010111111010010111111011010111111100010111111101010111111110010111111111 "
b111111111111010111111001010111111010010111111011010111111100010111111101010111111110010111111111 )
b101000000110 #
b101000000110 '
b1000000 $
b1000000 (
b110 &
#77000
b111111111111010111111001010111111010010111111011010111111100010111111101010111111110010111111111 ,
#78000
b10111111000010111111001010111111010010111111011010111111100010111111101010111111110010111111111 "
b10111111000010111111001010111111010010111111011010111111100010111111101010111111110010111111111 )
b101000000111 #
b101000000111 '
b10000000 $
b10000000 (
b111 &
#88000
b10111111000010111111001010111111010010111111011010111111100010111111101010111111110010111111111 ,
#89000
b0 $
b0 (
b1000 &
#100000
b10111111000010111111001010111111010001001000001010111111100010111111101010111111110010111111111 "
b10111111000010111111001010111111010001001000001010111111100010111111101010111111110010111111111 )
b111111111111111111111111111111111111001000010101111111111111111111111111111111111111111111111111 !
b111111111111111111111111111111111111001000010101111111111111111111111111111111111111111111111111 *
b110111101010110110111110 #
b110111101010110110111110 '
b10000 $
b10000 (
#110000
b111111111111111111111111111111111111001000010101111111111111111111111111111111111111111111111111 -
b10111111000010111111001010111111010001001000001010111111100010111111101010111111110010111111111 ,
#111000
b0 $
b0 (
#122000
b111111111111111111111111 #
b111111111111111111111111 '
