DCIM_Macro/rtl/s_cla.v
// 最终的、高性能的24位分块先行进位加法器 (s_cla) - 完全展开版本
module s_cla(
    input [23:0] a,
    input [23:0] b,
    input cin,
    output [23:0] sum
);

    // --- 信号定义 ---
    wire [23:0] g, p;
    wire [5:0]  bg, bp;
    wire [6:0]  c_block;
    wire [24:0] c; // 最终的逐位进位

    // --- 1. 计算每一位的 g 和 p ---
    assign g = a & b;
    assign p = a ^ b;

    // --- 2. 计算每个4-bit块的 bg 和 bp ---
    assign bg[0] = g[3] | (p[3] & g[2]) | (p[3] & p[2] & g[1]) | (p[3] & p[2] & p[1] & g[0]);
    assign bp[0] = p[3] & p[2] & p[1] & p[0];
    assign bg[1] = g[7] | (p[7] & g[6]) | (p[7] & p[6] & g[5]) | (p[7] & p[6] & p[5] & g[4]);
    assign bp[1] = p[7] & p[6] & p[5] & p[4];
    assign bg[2] = g[11] | (p[11] & g[10]) | (p[11] & p[10] & g[9]) | (p[11] & p[10] & p[9] & g[8]);
    assign bp[2] = p[11] & p[10] & p[9] & p[8];
    assign bg[3] = g[15] | (p[15] & g[14]) | (p[15] & p[14] & g[13]) | (p[15] & p[14] & p[13] & g[12]);
    assign bp[3] = p[15] & p[14] & p[13] & p[12];
    assign bg[4] = g[19] | (p[19] & g[18]) | (p[19] & p[18] & g[17]) | (p[19] & p[18] & p[17] & g[16]);
    assign bp[4] = p[19] & p[18] & p[17] & p[16];
    assign bg[5] = g[23] | (p[23] & g[22]) | (p[23] & p[22] & g[21]) | (p[23] & p[22] & p[21] & g[20]);
    assign bp[5] = p[23] & p[22] & p[21] & p[20];

    // --- 3. 计算块间进位 ---
    assign c_block[0] = cin;
    assign c_block[1] = bg[0] | (bp[0] & c_block[0]);
    assign c_block[2] = bg[1] | (bp[1] & c_block[1]);
    assign c_block[3] = bg[2] | (bp[2] & c_block[2]);
    assign c_block[4] = bg[3] | (bp[3] & c_block[3]);
    assign c_block[5] = bg[4] | (bp[4] & c_block[4]);
    assign c_block[6] = bg[5] | (bp[5] & c_block[5]);

    // --- 4. 计算最终的逐位进位 c[24:0] ---
    assign c[0] = c_block[0];
    assign c[1] = g[0] | (p[0] & c[0]);
    assign c[2] = g[1] | (p[1] & c[1]);
    assign c[3] = g[2] | (p[2] & c[2]);
    assign c[4] = c_block[1];
    assign c[5] = g[4] | (p[4] & c[4]);
    assign c[6] = g[5] | (p[5] & c[5]);
    assign c[7] = g[6] | (p[6] & c[6]);
    assign c[8] = c_block[2];
    assign c[9] = g[8] | (p[8] & c[8]);
    assign c[10] = g[9] | (p[9] & c[9]);
    assign c[11] = g[10] | (p[10] & c[10]);
    assign c[12] = c_block[3];
    assign c[13] = g[12] | (p[12] & c[12]);
    assign c[14] = g[13] | (p[13] & c[13]);
    assign c[15] = g[14] | (p[14] & c[14]);
    assign c[16] = c_block[4];
    assign c[17] = g[16] | (p[16] & c[16]);
    assign c[18] = g[17] | (p[17] & c[17]);
    assign c[19] = g[18] | (p[18] & c[18]);
    assign c[20] = c_block[5];
    assign c[21] = g[20] | (p[20] & c[20]);
    assign c[22] = g[21] | (p[21] & c[21]);
    assign c[23] = g[22] | (p[22] & c[22]);
    assign c[24] = c_block[6]; // Final carry-out

    // --- 5. 计算最终的和 (sum) ---
    assign sum = p ^ c[23:0];

endmodule

DCIM_Macro/tb_verify/tb_verify_s_cla.v
`timescale 1ns / 1ps

module tb_verify_s_cla;

    // Inputs
    reg [23:0] a;
    reg [23:0] b;
    reg cin;

    // Outputs
    wire [23:0] sum;

    // Instantiate the Unit Under Test (UUT)
    s_cla uut (
        .a(a),
        .b(b),
        .cin(cin),
        .sum(sum)
    );

    integer errors = 0;

    // Verification task
    task check_output;
        input [23:0] expected_sum;
        begin
            #10;
            if (sum !== expected_sum) begin
                $display("ERROR: a=%h, b=%h, cin=%b -> sum=%h (expected %h)", a, b, cin, sum, expected_sum);
                errors = errors + 1;
            end
        end
    endtask

    initial begin
        // Initialize Inputs
        a = 0;
        b = 0;
        cin = 0;

        $dumpfile("tb_verify_s_cla.vcd");
        $dumpvars(0, tb_verify_s_cla);

        // Test Case 1: Zero test
        $display("--- Verification Case 1: Zero Test ---");
        a = 24'd0; b = 24'd0; cin = 0; check_output(24'd0);

        // Test Case 2: Basic addition
        $display("--- Verification Case 2: Basic Addition ---");
        a = 24'd12345; b = 24'd54321; cin = 0; check_output(24'd66666);
        a = 24'd10; b = 24'd20; cin = 1; check_output(24'd31);

        // Test Case 3: Max values and overflow
        $display("--- Verification Case 3: Max values and overflow ---");
        a = 24'hFFFFFF; b = 24'h000000; cin = 0; check_output(24'hFFFFFF);
        a = 24'hFFFFFF; b = 24'h000001; cin = 0; check_output(24'h000000);
        a = 24'hFFFFFF; b = 24'hFFFFFF; cin = 1; check_output(24'hFFFFFF);

        // Test Case 5: Signed-like addition (pos + neg)
        $display("--- Verification Case 5: Signed-like addition ---");
        a = 24'd100; b = -24'sd50; cin = 0; check_output(24'd50);
        a = -24'sd100; b = 24'd50; cin = 0; check_output(-24'sd50);
        a = -24'sd100; b = -24'sd50; cin = 0; check_output(-24'sd150);

        // Final result
        #20;
        if (errors == 0)
            $display("--- VERIFICATION PASSED ---");
        else
            $display("--- VERIFICATION FAILED: %0d errors ---", errors);

        $finish;
    end

endmodule

DCIM_Macro/tb_verify_s_cla.vcd
$date
	Sat Aug 09 02:11:18 2025
$end
$version
	Icarus Verilog
$end
$timescale
	1ps
$end
$scope module tb_verify_s_cla $end
$var wire 24 ! sum [23:0] $end
$var reg 24 " a [23:0] $end
$var reg 24 # b [23:0] $end
$var reg 1 $ cin $end
$var integer 32 % errors [31:0] $end
$scope module uut $end
$var wire 24 & a [23:0] $end
$var wire 24 ' b [23:0] $end
$var wire 1 $ cin $end
$var wire 24 ( g [23:0] $end
$var wire 24 ) p [23:0] $end
$var wire 24 * sum [23:0] $end
$var wire 7 + c_block [6:0] $end
$var wire 25 , c [24:0] $end
$var wire 6 - bp [5:0] $end
$var wire 6 . bg [5:0] $end
$upscope $end
$scope task check_output $end
$var reg 24 / expected_sum [23:0] $end
$upscope $end
$upscope $end
$enddefinitions $end
$comment Show the parameter values. $end
$dumpall
$end
#0
$dumpvars
b0 /
b0 .
b0 -
b0 ,
b0 +
b0 *
b0 )
b0 (
b0 '
b0 &
b0 %
0$
b0 #
b0 "
b0 !
$end
#10000
b10000 +
b1000 .
b11110000001100010 ,
b10000010001101010 !
b10000010001101010 *
b1000000110001 (
b1110010000001000 )
b10000010001101010 /
b1101010000110001 #
b1101010000110001 '
b11000000111001 "
b11000000111001 &
#20000
b0 .
b11111 !
b11111 *
b1 ,
b0 (
b11110 )
b11111 /
b1 +
1$
b10100 #
b10100 '
b1010 "
b1010 &
#30000
b111111 -
b111111111111111111111111 !
b111111111111111111111111 *
b0 ,
b111111111111111111111111 )
b111111111111111111111111 /
b0 +
0$
b0 #
b0 '
b111111111111111111111111 "
b111111111111111111111111 &
#40000
b1111110 +
b1 .
b1111111111111111111111110 ,
b111110 -
b0 !
b0 *
b1 (
b111111111111111111111110 )
b0 /
b1 #
b1 '
#50000
b111111 .
b0 -
b111111111111111111111111 !
b111111111111111111111111 *
b1111111111111111111111111 ,
b111111111111111111111111 (
b0 )
b111111111111111111111111 /
b1111111 +
1$
b111111111111111111111111 #
b111111111111111111111111 '
#60000
b11 .
b111100 -
b110010 !
b110010 *
b1111111111111111110011000 ,
b1000100 (
b111111111111111110101010 )
b110010 /
b1111110 +
0$
b111111111111111111001110 #
b111111111111111111001110 '
b1100100 "
b1100100 &
#70000
b0 +
b0 .
b1100000 ,
b111111111111111111001110 !
b111111111111111111001110 *
b10000 (
b111111111111111110101110 )
b111111111111111111001110 /
b110010 #
b110010 '
b111111111111111110011100 "
b111111111111111110011100 &
#80000
b1111110 +
b111111 .
b1111111111111111100111000 ,
b0 -
b111111111111111101101010 !
b111111111111111101101010 *
b111111111111111110001100 (
b1010010 )
b111111111111111101101010 /
b111111111111111111001110 #
b111111111111111111001110 '
