DCIM_Macro/rtl/s_cla.v
// 最终的、高性能的24位分块先行进位加法器 (s_cla) - 完全展开版本
module s_cla(
    input [23:0] a,
    input [23:0] b,
    input cin,
    output [23:0] sum
);

    // --- 信号定义 ---
    wire [23:0] g, p;
    wire [5:0]  bg, bp;
    wire [6:0]  c_block;
    wire [24:0] c; // 最终的逐位进位

    // --- 1. 计算每一位的 g 和 p ---
    assign g = a & b;
    assign p = a ^ b;

    // --- 2. 计算每个4-bit块的 bg 和 bp ---
    assign bg[0] = g[3] | (p[3] & g[2]) | (p[3] & p[2] & g[1]) | (p[3] & p[2] & p[1] & g[0]);
    assign bp[0] = p[3] & p[2] & p[1] & p[0];
    assign bg[1] = g[7] | (p[7] & g[6]) | (p[7] & p[6] & g[5]) | (p[7] & p[6] & p[5] & g[4]);
    assign bp[1] = p[7] & p[6] & p[5] & p[4];
    assign bg[2] = g[11] | (p[11] & g[10]) | (p[11] & p[10] & g[9]) | (p[11] & p[10] & p[9] & g[8]);
    assign bp[2] = p[11] & p[10] & p[9] & p[8];
    assign bg[3] = g[15] | (p[15] & g[14]) | (p[15] & p[14] & g[13]) | (p[15] & p[14] & p[13] & g[12]);
    assign bp[3] = p[15] & p[14] & p[13] & p[12];
    assign bg[4] = g[19] | (p[19] & g[18]) | (p[19] & p[18] & g[17]) | (p[19] & p[18] & p[17] & g[16]);
    assign bp[4] = p[19] & p[18] & p[17] & p[16];
    assign bg[5] = g[23] | (p[23] & g[22]) | (p[23] & p[22] & g[21]) | (p[23] & p[22] & p[21] & g[20]);
    assign bp[5] = p[23] & p[22] & p[21] & p[20];

    // --- 3. 计算块间进位 ---
    assign c_block[0] = cin;
    assign c_block[1] = bg[0] | (bp[0] & c_block[0]);
    assign c_block[2] = bg[1] | (bp[1] & c_block[1]);
    assign c_block[3] = bg[2] | (bp[2] & c_block[2]);
    assign c_block[4] = bg[3] | (bp[3] & c_block[3]);
    assign c_block[5] = bg[4] | (bp[4] & c_block[4]);
    assign c_block[6] = bg[5] | (bp[5] & c_block[5]);

    // --- 4. 计算最终的逐位进位 c[24:0] ---
    assign c[0] = c_block[0];
    assign c[1] = g[0] | (p[0] & c[0]);
    assign c[2] = g[1] | (p[1] & c[1]);
    assign c[3] = g[2] | (p[2] & c[2]);
    assign c[4] = c_block[1];
    assign c[5] = g[4] | (p[4] & c[4]);
    assign c[6] = g[5] | (p[5] & c[5]);
    assign c[7] = g[6] | (p[6] & c[6]);
    assign c[8] = c_block[2];
    assign c[9] = g[8] | (p[8] & c[8]);
    assign c[10] = g[9] | (p[9] & c[9]);
    assign c[11] = g[10] | (p[10] & c[10]);
    assign c[12] = c_block[3];
    assign c[13] = g[12] | (p[12] & c[12]);
    assign c[14] = g[13] | (p[13] & c[13]);
    assign c[15] = g[14] | (p[14] & c[14]);
    assign c[16] = c_block[4];
    assign c[17] = g[16] | (p[16] & c[16]);
    assign c[18] = g[17] | (p[17] & c[17]);
    assign c[19] = g[18] | (p[18] & c[18]);
    assign c[20] = c_block[5];
    assign c[21] = g[20] | (p[20] & c[20]);
    assign c[22] = g[21] | (p[21] & c[21]);
    assign c[23] = g[22] | (p[22] & c[22]);
    assign c[24] = c_block[6]; // Final carry-out

    // --- 5. 计算最终的和 (sum) ---
    assign sum = p ^ c[23:0];

endmodule

DCIM_Macro/rtl/add.v
module add #(
    parameter width = 12      // 默认位宽为12
)(
    input [width-1:0] a,      // 输入a
    input [width-1:0] b,      // 输入b
    input sus,                // 有符号/无符号控制
    output wire [width:0] sum // 加法结果
);

    // 有符号加法：进行符号位扩展
    wire [width:0] a_signed, b_signed;
    
    // 根据sus信号决定是否进行符号扩展
    assign a_signed = sus ? {a[width-1], a} : {1'b0, a};
    assign b_signed = sus ? {b[width-1], b} : {1'b0, b};
    
    // 执行加法
    assign sum = a_signed + b_signed;

endmodule

DCIM_Macro/rtl/se_cla.v
module se_cla(
    input [26:0] a,           // 27位输入
    input [50:0] b,           // 51位输入
    output [50:0] sum         // 51位输出
);

    // 对27位输入a进行符号位扩展
    wire [50:0] a_ext;
    assign a_ext = {{24{a[26]}}, a};  // 符号位扩展
    
    // 低27位加法
    wire [26:0] sum_low;
    wire carry_out;
    
    add #(.width(27)) add_low(
        .a(a),
        .b(b[26:0]),
        .sus(1'b0),  // 无符号加法
        .sum({carry_out, sum_low})
    );
    
    // 高24位加法（考虑进位）
    wire [23:0] sum_high;
    
    s_cla s_cla_inst(
        .a(a_ext[50:27]),
        .b(b[50:27]),
        .cin(carry_out),
        .sum(sum_high)
    );
    
    // 拼接结果
    assign sum = {sum_high, sum_low};

endmodule

DCIM_Macro/rtl/accumulator.v
// 最终的、实例化se_cla的、电路稳定的累加器
module accumulator(
    input [26:0] a,
    input clk,
    input acm_en,
    input rstn,
    input st,
    output [50:0] nout
);

    // 内部累加寄存器
    reg [50:0] nout_1;
    
    // 模块输出直接来自寄存器
    assign nout = nout_1;

    // --- 用于计算的中间信号 ---
    wire [50:0] shifted_nout_1; // 用于存放 nout_1 << 1 的结果
    wire [50:0] sum_result;     // 加法器的输出

    // --- 组合逻辑部分 ---
    // 1. 对当前寄存器的值进行左移一位
    assign shifted_nout_1 = {nout_1[49:0], 1'b0};

    // 2. 实例化 se_cla 加法器来计算：(nout_1 << 1) + a
    se_cla se_cla_inst (
        .a(a),
        .b(shifted_nout_1),
        .sum(sum_result)
    );

    // --- 时序逻辑部分 ---
    // 在时钟边沿，用预先计算好的、稳定的加法结果来更新寄存器
    always @(posedge clk or negedge rstn) begin
        if (!rstn) begin
            nout_1 <= 51'b0;
        end else if (acm_en) begin
            if (st) begin
                nout_1 <= 51'b0;
            end else begin
                // 锁存稳定的加法结果
                nout_1 <= sum_result;
            end
        end
    end

endmodule

DCIM_Macro/tb_verify/tb_verify_accumulator.v
`timescale 1ns / 1ps

module tb_verify_accumulator;

    // Inputs
    reg [26:0] a;
    reg clk;
    reg acm_en;
    reg rstn;
    reg st;

    // Outputs
    wire [50:0] nout;

    // Instantiate the Unit Under Test (UUT)
    accumulator uut (
        .a(a),
        .clk(clk),
        .acm_en(acm_en),
        .rstn(rstn),
        .st(st),
        .nout(nout)
    );

    integer errors = 0;

    // Clock generation
    initial begin
        clk = 0;
        forever #5 clk = ~clk;
    end

    // Verification task
    task check_output;
        input [50:0] expected_nout;
        begin
            #1; // Allow for combinational logic to settle
            if (nout !== expected_nout) begin
                $display("ERROR @ Time=%0t: nout = %d (expected %d)", $time, nout, expected_nout);
                errors = errors + 1;
            end
        end
    endtask

    initial begin
        // Initialize Inputs
        a = 0;
        acm_en = 0;
        rstn = 0;
        st = 1;

        $dumpfile("tb_verify_accumulator.vcd");
        $dumpvars(0, tb_verify_accumulator);

        // Test Case 1: Reset
        $display("--- Verification Case 1: Reset ---");
        #10;
        rstn = 1;
        #10;
        check_output(0);

        // Test Case 2: Accumulation disabled
        $display("--- Verification Case 2: Accumulation disabled (acm_en=0) ---");
        acm_en = 0;
        st = 0;
        a = 100;
        #20; // Wait for a few clock cycles
        check_output(0);

        // Test Case 3: Accumulation enabled and running
        $display("--- Verification Case 3: Accumulation enabled and running ---");
        acm_en = 1;
        st = 0;
        a = 10; @(posedge clk); check_output(10);
        a = 20; @(posedge clk); check_output(40);
        a = 30; @(posedge clk); check_output(110);
        a = 0;  @(posedge clk); check_output(220);

        // Test Case 4: 'st' signal stops and resets accumulation
        $display("--- Verification Case 4: 'st' signal high ---");
        st = 1;
        a = 999; // This value should be ignored
        @(posedge clk);
        check_output(0);
        st = 0;
        a = 5;
        @(posedge clk);
        check_output(5);

        // Test Case 5: Negative reset
        $display("--- Verification Case 5: Negative reset (rstn=0) ---");
        rstn = 0;
        #10;
        check_output(0);

        // Final result
        #20;
        if (errors == 0)
            $display("--- VERIFICATION PASSED ---");
        else
            $display("--- VERIFICATION FAILED: %0d errors ---", errors);

        $finish;
    end

endmodule

DCIM_Macro/tb_verify_accumulator.vcd
$date
	Sat Aug 09 02:11:22 2025
$end
$version
	Icarus Verilog
$end
$timescale
	1ps
$end
$scope module tb_verify_accumulator $end
$var wire 51 ! nout [50:0] $end
$var reg 27 " a [26:0] $end
$var reg 1 # acm_en $end
$var reg 1 $ clk $end
$var reg 1 % rstn $end
$var reg 1 & st $end
$var integer 32 ' errors [31:0] $end
$scope module uut $end
$var wire 27 ( a [26:0] $end
$var wire 1 # acm_en $end
$var wire 1 $ clk $end
$var wire 51 ) nout [50:0] $end
$var wire 1 % rstn $end
$var wire 1 & st $end
$var wire 51 * sum_result [50:0] $end
$var wire 51 + shifted_nout_1 [50:0] $end
$var reg 51 , nout_1 [50:0] $end
$scope module se_cla_inst $end
$var wire 27 - a [26:0] $end
$var wire 51 . b [50:0] $end
$var wire 27 / sum_low [26:0] $end
$var wire 24 0 sum_high [23:0] $end
$var wire 51 1 sum [50:0] $end
$var wire 1 2 carry_out $end
$var wire 51 3 a_ext [50:0] $end
$scope module add_low $end
$var wire 27 4 a [26:0] $end
$var wire 28 5 a_signed [27:0] $end
$var wire 27 6 b [26:0] $end
$var wire 28 7 b_signed [27:0] $end
$var wire 1 8 sus $end
$var wire 28 9 sum [27:0] $end
$var parameter 32 : width $end
$upscope $end
$scope module s_cla_inst $end
$var wire 24 ; a [23:0] $end
$var wire 24 < b [23:0] $end
$var wire 1 2 cin $end
$var wire 24 = g [23:0] $end
$var wire 24 > p [23:0] $end
$var wire 24 ? sum [23:0] $end
$var wire 7 @ c_block [6:0] $end
$var wire 25 A c [24:0] $end
$var wire 6 B bp [5:0] $end
$var wire 6 C bg [5:0] $end
$upscope $end
$upscope $end
$upscope $end
$scope task check_output $end
$var reg 51 D expected_nout [50:0] $end
$upscope $end
$upscope $end
$enddefinitions $end
$comment Show the parameter values. $end
$dumpall
b11011 :
$end
#0
$dumpvars
bx D
b0 C
b0 B
b0 A
b0 @
b0 ?
b0 >
b0 =
b0 <
b0 ;
b0 9
08
b0 7
b0 6
b0 5
b0 4
b0 3
02
b0 1
b0 0
b0 /
b0 .
b0 -
b0 ,
b0 +
b0 *
b0 )
b0 (
b0 '
1&
0%
0$
0#
b0 "
b0 !
$end
#5000
1$
#10000
0$
1%
#15000
1$
#20000
0$
b0 D
#21000
b1100100 *
b1100100 1
b1100100 /
b1100100 3
b1100100 9
b1100100 5
b1100100 "
b1100100 (
b1100100 -
b1100100 4
0&
#25000
1$
#30000
0$
#35000
1$
#40000
0$
#42000
b1010 *
b1010 1
b1010 /
b1010 3
b1010 9
b1010 5
b1010 "
b1010 (
b1010 -
b1010 4
1#
#45000
b11110 *
b11110 1
b11110 /
b11110 9
b10100 7
b10100 6
b10100 +
b10100 .
b1010 !
b1010 )
b1010 ,
b1010 D
1$
#46000
b101000 *
b101000 1
b101000 /
b10100 3
b101000 9
b10100 5
b10100 "
b10100 (
b10100 -
b10100 4
#50000
0$
#55000
b1100100 *
b1100100 1
b1100100 /
b1100100 9
b1010000 7
b1010000 6
b1010000 +
b1010000 .
b101000 !
b101000 )
b101000 ,
b101000 D
1$
#56000
b1101110 *
b1101110 1
b1101110 /
b11110 3
b1101110 9
b11110 5
b11110 "
b11110 (
b11110 -
b11110 4
#60000
0$
#65000
b11111010 *
b11111010 1
b11111010 /
b11111010 9
b11011100 7
b11011100 6
b11011100 +
b11011100 .
b1101110 !
b1101110 )
b1101110 ,
b1101110 D
1$
#66000
b11011100 *
b11011100 1
b11011100 /
b0 3
b11011100 9
b0 5
b0 "
b0 (
b0 -
b0 4
#70000
0$
#75000
b110111000 *
b110111000 1
b110111000 /
b110111000 9
b110111000 7
b110111000 6
b110111000 +
b110111000 .
b11011100 !
b11011100 )
b11011100 ,
b11011100 D
1$
#76000
b10110011111 *
b10110011111 1
b10110011111 /
b1111100111 3
b10110011111 9
b1111100111 5
b1111100111 "
b1111100111 (
b1111100111 -
b1111100111 4
1&
#80000
0$
#85000
b1111100111 *
b1111100111 1
b1111100111 /
b1111100111 9
b0 7
b0 6
b0 +
b0 .
b0 !
b0 )
b0 ,
b0 D
1$
#86000
b101 *
b101 1
b101 /
b101 3
b101 9
b101 5
b101 "
b101 (
b101 -
b101 4
0&
#90000
0$
#95000
b1111 *
b1111 1
b1111 /
b1111 9
b1010 7
b1010 6
b1010 +
b1010 .
b101 !
b101 )
b101 ,
b101 D
1$
#96000
b101 *
b101 1
b101 /
b101 9
b0 7
b0 6
b0 +
b0 .
b0 !
b0 )
b0 ,
0%
#100000
0$
#105000
1$
#106000
b0 D
