DCIM_Macro/rtl/s_cla.v
// 最终的、高性能的24位分块先行进位加法器 (s_cla) - 完全展开版本
module s_cla(
    input [23:0] a,
    input [23:0] b,
    input cin,
    output [23:0] sum
);

    // --- 信号定义 ---
    wire [23:0] g, p;
    wire [5:0]  bg, bp;
    wire [6:0]  c_block;
    wire [24:0] c; // 最终的逐位进位

    // --- 1. 计算每一位的 g 和 p ---
    assign g = a & b;
    assign p = a ^ b;

    // --- 2. 计算每个4-bit块的 bg 和 bp ---
    assign bg[0] = g[3] | (p[3] & g[2]) | (p[3] & p[2] & g[1]) | (p[3] & p[2] & p[1] & g[0]);
    assign bp[0] = p[3] & p[2] & p[1] & p[0];
    assign bg[1] = g[7] | (p[7] & g[6]) | (p[7] & p[6] & g[5]) | (p[7] & p[6] & p[5] & g[4]);
    assign bp[1] = p[7] & p[6] & p[5] & p[4];
    assign bg[2] = g[11] | (p[11] & g[10]) | (p[11] & p[10] & g[9]) | (p[11] & p[10] & p[9] & g[8]);
    assign bp[2] = p[11] & p[10] & p[9] & p[8];
    assign bg[3] = g[15] | (p[15] & g[14]) | (p[15] & p[14] & g[13]) | (p[15] & p[14] & p[13] & g[12]);
    assign bp[3] = p[15] & p[14] & p[13] & p[12];
    assign bg[4] = g[19] | (p[19] & g[18]) | (p[19] & p[18] & g[17]) | (p[19] & p[18] & p[17] & g[16]);
    assign bp[4] = p[19] & p[18] & p[17] & p[16];
    assign bg[5] = g[23] | (p[23] & g[22]) | (p[23] & p[22] & g[21]) | (p[23] & p[22] & p[21] & g[20]);
    assign bp[5] = p[23] & p[22] & p[21] & p[20];

    // --- 3. 计算块间进位 ---
    assign c_block[0] = cin;
    assign c_block[1] = bg[0] | (bp[0] & c_block[0]);
    assign c_block[2] = bg[1] | (bp[1] & c_block[1]);
    assign c_block[3] = bg[2] | (bp[2] & c_block[2]);
    assign c_block[4] = bg[3] | (bp[3] & c_block[3]);
    assign c_block[5] = bg[4] | (bp[4] & c_block[4]);
    assign c_block[6] = bg[5] | (bp[5] & c_block[5]);

    // --- 4. 计算最终的逐位进位 c[24:0] ---
    assign c[0] = c_block[0];
    assign c[1] = g[0] | (p[0] & c[0]);
    assign c[2] = g[1] | (p[1] & c[1]);
    assign c[3] = g[2] | (p[2] & c[2]);
    assign c[4] = c_block[1];
    assign c[5] = g[4] | (p[4] & c[4]);
    assign c[6] = g[5] | (p[5] & c[5]);
    assign c[7] = g[6] | (p[6] & c[6]);
    assign c[8] = c_block[2];
    assign c[9] = g[8] | (p[8] & c[8]);
    assign c[10] = g[9] | (p[9] & c[9]);
    assign c[11] = g[10] | (p[10] & c[10]);
    assign c[12] = c_block[3];
    assign c[13] = g[12] | (p[12] & c[12]);
    assign c[14] = g[13] | (p[13] & c[13]);
    assign c[15] = g[14] | (p[14] & c[14]);
    assign c[16] = c_block[4];
    assign c[17] = g[16] | (p[16] & c[16]);
    assign c[18] = g[17] | (p[17] & c[17]);
    assign c[19] = g[18] | (p[18] & c[18]);
    assign c[20] = c_block[5];
    assign c[21] = g[20] | (p[20] & c[20]);
    assign c[22] = g[21] | (p[21] & c[21]);
    assign c[23] = g[22] | (p[22] & c[22]);
    assign c[24] = c_block[6]; // Final carry-out

    // --- 5. 计算最终的和 (sum) ---
    assign sum = p ^ c[23:0];

endmodule

DCIM_Macro/rtl/add.v
module add #(
    parameter width = 12      // 默认位宽为12
)(
    input [width-1:0] a,      // 输入a
    input [width-1:0] b,      // 输入b
    input sus,                // 有符号/无符号控制
    output wire [width:0] sum // 加法结果
);

    // 有符号加法：进行符号位扩展
    wire [width:0] a_signed, b_signed;
    
    // 根据sus信号决定是否进行符号扩展
    assign a_signed = sus ? {a[width-1], a} : {1'b0, a};
    assign b_signed = sus ? {b[width-1], b} : {1'b0, b};
    
    // 执行加法
    assign sum = a_signed + b_signed;

endmodule

DCIM_Macro/rtl/se_cla.v
module se_cla(
    input [26:0] a,           // 27位输入
    input [50:0] b,           // 51位输入
    output [50:0] sum         // 51位输出
);

    // 对27位输入a进行符号位扩展
    wire [50:0] a_ext;
    assign a_ext = {{24{a[26]}}, a};  // 符号位扩展
    
    // 低27位加法
    wire [26:0] sum_low;
    wire carry_out;
    
    add #(.width(27)) add_low(
        .a(a),
        .b(b[26:0]),
        .sus(1'b0),  // 无符号加法
        .sum({carry_out, sum_low})
    );
    
    // 高24位加法（考虑进位）
    wire [23:0] sum_high;
    
    s_cla s_cla_inst(
        .a(a_ext[50:27]),
        .b(b[50:27]),
        .cin(carry_out),
        .sum(sum_high)
    );
    
    // 拼接结果
    assign sum = {sum_high, sum_low};

endmodule

DCIM_Macro/tb_verify/tb_verify_se_cla.v
`timescale 1ns / 1ps

module tb_verify_se_cla;

    // Inputs
    reg signed [26:0] a;
    reg signed [50:0] b;

    // Outputs
    wire signed [50:0] sum;

    // Instantiate the Unit Under Test (UUT)
    se_cla uut (
        .a(a),
        .b(b),
        .sum(sum)
    );

    integer errors = 0;

    // Verification task
    task check_output;
        input signed [50:0] expected_sum;  // 修改为51位宽以匹配实际输出
        begin
            #10;
            if (sum !== expected_sum) begin
                $display("ERROR: a=%d, b=%d -> sum=%d (expected %d)", a, b, sum, expected_sum);
                errors = errors + 1;
            end
        end
    endtask

    initial begin
        // Initialize Inputs
        a = 0;
        b = 0;

        $dumpfile("tb_verify_se_cla.vcd");
        $dumpvars(0, tb_verify_se_cla);

        // Test Case 1: Zero test
        $display("--- Verification Case 1: Zero Test ---");
        a = 27'sd0; b = 51'sd0; check_output(51'sd0);

        // Test Case 2: Positive 'a', Positive 'b'
        $display("--- Verification Case 2: Positive 'a', Positive 'b' ---");
        a = 27'sd12345; b = 51'sd5432109876; check_output(51'sd5432122221);

        // Test Case 3: Negative 'a', Positive 'b'
        $display("--- Verification Case 3: Negative 'a', Positive 'b' ---");
        a = -27'sd12345; b = 51'sd5432109876; check_output(51'sd5432097531);
        a = -27'sd1; b = 51'sd1; check_output(51'sd0);

        // Test Case 4: Large values (修正期望值)
        $display("--- Verification Case 4: Large values ---");
        a = 27'sh7FFFFFF;  // 134217727
        b = 51'h7FFFFFFFFFFFF; 
        check_output(-51'sd2);
        
        a = -27'sh8000000;  // -134217728
        b = 51'sd0; 
        check_output(51'sd0);
        
        a = -27'sh8000000;  // -134217728
        b = 51'h7FFFFFFFFFFFF; 
        check_output(-51'sd1);
        
        // Test Case 5: Negative 'b' (修正期望值)
        $display("--- Verification Case 5: Negative 'b' ---");
        a = 27'sd1000; b = -51'sd500; check_output(51'sd500);
        a = -27'sd1000; b = -51'sd500; check_output(-51'sd1500);
        a = 27'sd123; b = -51'sd456789; check_output(-51'sd456666);

        // Final result
        #20;
        if (errors == 0)
            $display("--- VERIFICATION PASSED ---");
        else
            $display("--- VERIFICATION FAILED: %0d errors ---", errors);

        $finish;
    end

endmodule

DCIM_Macro/tb_verify_se_cla.vcd
$date
	Sat Aug 09 02:11:20 2025
$end
$version
	Icarus Verilog
$end
$timescale
	1ps
$end
$scope module tb_verify_se_cla $end
$var wire 51 ! sum [50:0] $end
$var reg 27 " a [26:0] $end
$var reg 51 # b [50:0] $end
$var integer 32 $ errors [31:0] $end
$scope module uut $end
$var wire 27 % a [26:0] $end
$var wire 51 & b [50:0] $end
$var wire 27 ' sum_low [26:0] $end
$var wire 24 ( sum_high [23:0] $end
$var wire 51 ) sum [50:0] $end
$var wire 1 * carry_out $end
$var wire 51 + a_ext [50:0] $end
$scope module add_low $end
$var wire 27 , a [26:0] $end
$var wire 28 - a_signed [27:0] $end
$var wire 27 . b [26:0] $end
$var wire 28 / b_signed [27:0] $end
$var wire 1 0 sus $end
$var wire 28 1 sum [27:0] $end
$var parameter 32 2 width $end
$upscope $end
$scope module s_cla_inst $end
$var wire 24 3 a [23:0] $end
$var wire 24 4 b [23:0] $end
$var wire 1 * cin $end
$var wire 24 5 g [23:0] $end
$var wire 24 6 p [23:0] $end
$var wire 24 7 sum [23:0] $end
$var wire 7 8 c_block [6:0] $end
$var wire 25 9 c [24:0] $end
$var wire 6 : bp [5:0] $end
$var wire 6 ; bg [5:0] $end
$upscope $end
$upscope $end
$scope task check_output $end
$var reg 51 < expected_sum [50:0] $end
$upscope $end
$upscope $end
$enddefinitions $end
$comment Show the parameter values. $end
$dumpall
b11011 2
$end
#0
$dumpvars
b0 <
b0 ;
b0 :
b0 9
b0 8
b0 7
b0 6
b0 5
b0 4
b0 3
b0 1
00
b0 /
b0 .
b0 -
b0 ,
b0 +
0*
b0 )
b0 (
b0 '
b0 &
b0 %
b0 $
b0 #
b0 "
b0 !
$end
#10000
b101000 (
b101000 7
b101000 6
b11110001110110101100110100 /
b11110001110110101100110100 .
b101000 4
b101000011110001111001101101101101 !
b101000011110001111001101101101101 )
b11110001111001101101101101 '
b101000011110001111001101101101101 <
b101000011110001110110101100110100 #
b101000011110001110110101100110100 &
b11000000111001 +
b11110001111001101101101101 1
b11000000111001 -
b11000000111001 "
b11000000111001 %
b11000000111001 ,
#20000
b11 ;
b111100 :
b101000 (
b101000 7
b101000 5
b111111111111111111010111 6
b111111111111111111111111 3
b1111111111111111111111111 9
b101000011110001110011101011111011 !
b101000011110001110011101011111011 )
b11110001110011101011111011 '
b1111111 8
1*
b101000011110001110011101011111011 <
b111111111111111111111111111111111111100111111000111 +
b1011110001110011101011111011 1
b111111111111100111111000111 -
b111111111111100111111000111 "
b111111111111100111111000111 %
b111111111111100111111000111 ,
#30000
b0 ;
b111111 :
b0 (
b0 7
b0 5
b111111111111111111111111 6
b1 /
b1 .
b0 4
b0 !
b0 )
b0 '
b0 <
b1 #
b1 &
b111111111111111111111111111111111111111111111111111 +
b1000000000000000000000000000 1
b111111111111111111111111111 -
b111111111111111111111111111 "
b111111111111111111111111111 %
b111111111111111111111111111 ,
#40000
b1111111111111111111111111 9
b1111111 8
b111111 ;
b0 :
b111111111111111111111111 (
b111111111111111111111111 7
b111111111111111111111111111111111111111111111111110 !
b111111111111111111111111111111111111111111111111110 )
b111111111111111111111111110 '
b111111111111111111111111 5
b0 6
b1111111111111111111111111110 1
b111111111111111111111111111 /
b111111111111111111111111111 .
b111111111111111111111111 4
b111111111111111111111111111111111111111111111111110 <
b111111111111111111111111111111111111111111111111111 #
b111111111111111111111111111111111111111111111111111 &
#50000
b0 ;
b0 (
b0 7
b0 5
b0 3
b0 9
b0 /
b0 .
b0 4
b0 !
b0 )
b0 '
b0 8
0*
b0 <
b0 #
b0 &
b0 +
b0 1
b0 -
b0 "
b0 %
b0 ,
#60000
b111111 :
b111111111111111111111111 (
b111111111111111111111111 7
b111111111111111111111111111111111111111111111111111 !
b111111111111111111111111111111111111111111111111111 )
b111111111111111111111111111 '
b111111111111111111111111 6
b111111111111111111111111111 1
b111111111111111111111111111 /
b111111111111111111111111111 .
b111111111111111111111111 4
b111111111111111111111111111111111111111111111111111 <
b111111111111111111111111111111111111111111111111111 #
b111111111111111111111111111111111111111111111111111 &
#70000
b0 (
b0 7
b1111111111111111111111111 9
b111111111111111111000001100 /
b111111111111111111000001100 .
b111110100 !
b111110100 )
b111110100 '
b1111111 8
1*
b111110100 <
b111111111111111111111111111111111111111111000001100 #
b111111111111111111111111111111111111111111000001100 &
b1111101000 +
b1000000000000000000111110100 1
b1111101000 -
b1111101000 "
b1111101000 %
b1111101000 ,
#80000
b1111111111111111111111111 9
b1111111 8
b111111 ;
b0 :
b111111111111111111111111 (
b111111111111111111111111 7
b111111111111111111111111 5
b0 6
b111111111111111111111111 3
b111111111111111111111111111111111111111101000100100 !
b111111111111111111111111111111111111111101000100100 )
b111111111111111101000100100 '
b111111111111111111111111111111111111111101000100100 <
b111111111111111111111111111111111111111110000011000 +
b1111111111111111101000100100 1
b111111111111111110000011000 -
b111111111111111110000011000 "
b111111111111111110000011000 %
b111111111111111110000011000 ,
#90000
b0 ;
b111111 :
b111111111111111111111111 (
b111111111111111111111111 7
b0 5
b111111111111111111111111 6
b0 3
b0 9
b111111110010000011110101011 /
b111111110010000011110101011 .
b111111111111111111111111111111110010000100000100110 !
b111111111111111111111111111111110010000100000100110 )
b111111110010000100000100110 '
b0 8
0*
b111111111111111111111111111111110010000100000100110 <
b111111111111111111111111111111110010000011110101011 #
b111111111111111111111111111111110010000011110101011 &
b1111011 +
b111111110010000100000100110 1
b1111011 -
b1111011 "
b1111011 %
b1111011 ,
