DCIM_Macro/rtl/oai_mult.v
module oai_mult(
    input [11:0] a,           // 权重输入a
    input [11:0] b,           // 权重输入b
    input c,                  // 输入位c
    input d,                  // 输入位d
    output wire [11:0] e      // 乘法结果
);

    // OAI逻辑：e = ~((a | c) & (b | d))
    // 其中c和d是1位信号，需要扩展到12位
    wire [11:0] c_ext = {12{c}};  // 将c扩展到12位
    wire [11:0] d_ext = {12{d}};  // 将d扩展到12位
    
    // 实现OAI逻辑
    assign e = ~((a | c_ext) & (b | d_ext));

endmodule

DCIM_Macro/tb_verify/tb_verify_oai_mult.v
`timescale 1ns / 1ps

module tb_verify_oai_mult;

    // Inputs
    reg [11:0] a;
    reg [11:0] b;
    reg c;
    reg d;

    // Outputs
    wire [11:0] e;

    // Instantiate the Unit Under Test (UUT)
    oai_mult uut (
        .a(a),
        .b(b),
        .c(c),
        .d(d),
        .e(e)
    );

    integer errors = 0;

    // Verification task
    task check_output;
        input [11:0] expected_e;
        begin
            #10;
            if (e !== expected_e) begin
                $display("ERROR: a=%h, b=%h, c=%b, d=%b -> e=%h (expected %h)", a, b, c, d, e, expected_e);
                errors = errors + 1;
            end
        end
    endtask

    initial begin
        // Initialize Inputs
        a = 0;
        b = 0;
        c = 0;
        d = 0;

        $dumpfile("tb_verify_oai_mult.vcd");
        $dumpvars(0, tb_verify_oai_mult);

        // Test Case 1: c=0, d=0 => e = ~(a & b) (NAND)
        $display("--- Verification Case 1: c=0, d=0 (NAND logic) ---");
        c = 0; d = 0;
        a = 12'hFFF; b = 12'hFFF; check_output(12'h000);
        a = 12'hFFF; b = 12'h000; check_output(12'hFFF);
        a = 12'h000; b = 12'hFFF; check_output(12'hFFF);
        a = 12'h000; b = 12'h000; check_output(12'hFFF);
        a = 12'hF0F; b = 12'h0F0; check_output(12'hFFF);
        a = 12'hA5A; b = 12'h5A5; check_output(12'hFFF);

        // Test Case 2: c=0, d=1 => e = ~a (NOT a)
        $display("--- Verification Case 2: c=0, d=1 (NOT a logic) ---");
        c = 0; d = 1;
        a = 12'hFFF; b = 12'hFFF; check_output(12'h000);
        a = 12'h000; b = 12'hFFF; check_output(12'hFFF);
        a = 12'hF0F; b = 12'hFFF; check_output(12'h0F0);
        a = 12'hA5A; b = 12'hFFF; check_output(12'h5A5);

        // Test Case 3: c=1, d=0 => e = ~b (NOT b)
        $display("--- Verification Case 3: c=1, d=0 (NOT b logic) ---");
        c = 1; d = 0;
        a = 12'hFFF; b = 12'hFFF; check_output(12'h000);
        a = 12'hFFF; b = 12'h000; check_output(12'hFFF);
        a = 12'hFFF; b = 12'hF0F; check_output(12'h0F0);
        a = 12'hFFF; b = 12'hA5A; check_output(12'h5A5);

        // Test Case 4: c=1, d=1 => e = 0
        $display("--- Verification Case 4: c=1, d=1 (Output is always 0) ---");
        c = 1; d = 1;
        a = 12'hFFF; b = 12'hFFF; check_output(12'h000);
        a = 12'h000; b = 12'h000; check_output(12'h000);
        a = 12'hA5A; b = 12'h5A5; check_output(12'h000);

        // Final result
        #20;
        if (errors == 0)
            $display("--- VERIFICATION PASSED ---");
        else
            $display("--- VERIFICATION FAILED: %0d errors ---", errors);

        $finish;
    end

endmodule

DCIM_Macro/tb_verify_oai_mult.vcd
$date
	Sat Aug 09 02:11:13 2025
$end
$version
	Icarus Verilog
$end
$timescale
	1ps
$end
$scope module tb_verify_oai_mult $end
$var wire 12 ! e [11:0] $end
$var reg 12 " a [11:0] $end
$var reg 12 # b [11:0] $end
$var reg 1 $ c $end
$var reg 1 % d $end
$var integer 32 & errors [31:0] $end
$scope module uut $end
$var wire 12 ' a [11:0] $end
$var wire 12 ( b [11:0] $end
$var wire 1 $ c $end
$var wire 1 % d $end
$var wire 12 ) e [11:0] $end
$var wire 12 * d_ext [11:0] $end
$var wire 12 + c_ext [11:0] $end
$upscope $end
$scope task check_output $end
$var reg 12 , expected_e [11:0] $end
$upscope $end
$upscope $end
$enddefinitions $end
$comment Show the parameter values. $end
$dumpall
$end
#0
$dumpvars
b0 ,
b0 +
b0 *
b0 )
b111111111111 (
b111111111111 '
b0 &
0%
0$
b111111111111 #
b111111111111 "
b0 !
$end
#10000
b111111111111 !
b111111111111 )
b111111111111 ,
b0 #
b0 (
#20000
b111111111111 #
b111111111111 (
b0 "
b0 '
#30000
b0 #
b0 (
#40000
b11110000 #
b11110000 (
b111100001111 "
b111100001111 '
#50000
b10110100101 #
b10110100101 (
b101001011010 "
b101001011010 '
#60000
b0 !
b0 )
b0 ,
b111111111111 #
b111111111111 (
b111111111111 "
b111111111111 '
b111111111111 *
1%
#70000
b111111111111 !
b111111111111 )
b111111111111 ,
b0 "
b0 '
#80000
b11110000 !
b11110000 )
b11110000 ,
b111100001111 "
b111100001111 '
#90000
b10110100101 !
b10110100101 )
b10110100101 ,
b101001011010 "
b101001011010 '
#100000
b0 !
b0 )
b0 ,
b111111111111 "
b111111111111 '
b0 *
0%
b111111111111 +
1$
#110000
b111111111111 !
b111111111111 )
b111111111111 ,
b0 #
b0 (
#120000
b11110000 !
b11110000 )
b11110000 ,
b111100001111 #
b111100001111 (
#130000
b10110100101 !
b10110100101 )
b10110100101 ,
b101001011010 #
b101001011010 (
#140000
b0 !
b0 )
b0 ,
b111111111111 #
b111111111111 (
b111111111111 *
1%
#150000
b0 #
b0 (
b0 "
b0 '
#160000
b10110100101 #
b10110100101 (
b101001011010 "
b101001011010 '
