DCIM_Macro/rtl/cim_bank.v
module cim_bank(
    input [23:0] D,           // 写入数据
    input [7:0] WA,           // 写地址 (one-hot编码)
    output [95:0] wb_a,       // 权重输出A
    output [95:0] wb_b        // 权重输出B
);

    // 8x24-bit存储器数组
    reg [23:0] mem [7:0];

    // Initialize memory
    integer i;
    initial begin
        for (i = 0; i < 8; i = i + 1) begin
            mem[i] = 0;
        end
    end

    // 写操作 - 根据one-hot地址写入数据
    always @(*) begin
        case (WA)
            8'b00000001: mem[0] = D;
            8'b00000010: mem[1] = D;
            8'b00000100: mem[2] = D;
            8'b00001000: mem[3] = D;
            8'b00010000: mem[4] = D;
            8'b00100000: mem[5] = D;
            8'b01000000: mem[6] = D;
            8'b10000000: mem[7] = D;
            default: ; // 无操作
        endcase
    end

    // 读操作 - 持续输出所有存储单元内容的反相值，以实现AND逻辑
    // 将每个24-bit存储单元的低12位拼接并取反，作为 wb_a
    assign wb_a = ~{mem[7][11:0], mem[6][11:0], mem[5][11:0], mem[4][11:0],
                    mem[3][11:0], mem[2][11:0], mem[1][11:0], mem[0][11:0]};

    // 将每个24-bit存储单元的高12位拼接并取反，作为 wb_b
    assign wb_b = ~{mem[7][23:12], mem[6][23:12], mem[5][23:12], mem[4][23:12],
                    mem[3][23:12], mem[2][23:12], mem[1][23:12], mem[0][23:12]};

endmodule

DCIM_Macro/rtl/cim_array.v
module cim_array(
    input [23:0] D,           // 写入数据
    input [7:0] WA0, WA1,     // 写地址
    output [95:0] wb0_a, wb0_b,       // bank0权重输出
    output [95:0] wb1_a, wb1_b        // bank1权重输出
);

    // 实例化两个cim_bank
    cim_bank bank0_inst(
        .D(D),
        .WA(WA0),
        .wb_a(wb0_a),
        .wb_b(wb0_b)
    );

    cim_bank bank1_inst(
        .D(D),
        .WA(WA1),
        .wb_a(wb1_a),
        .wb_b(wb1_b)
    );

endmodule

DCIM_Macro/tb_verify/tb_verify_cim_array.v
`timescale 1ns / 1ps

module tb_verify_cim_array;

    // Inputs
    reg [23:0] D;
    reg [7:0] WA0;
    reg [7:0] WA1;

    // Outputs
    wire [95:0] wb0_a;
    wire [95:0] wb0_b;
    wire [95:0] wb1_a;
    wire [95:0] wb1_b;

    // Instantiate the Unit Under Test (UUT)
    cim_array uut (
        .D(D),
        .WA0(WA0),
        .WA1(WA1),
        .wb0_a(wb0_a),
        .wb0_b(wb0_b),
        .wb1_a(wb1_a),
        .wb1_b(wb1_b)
    );

    integer i;
    integer errors = 0;

    // Verification task
    task check_output;
        input [95:0] expected_wb0_a, expected_wb0_b, expected_wb1_a, expected_wb1_b;
        begin
            #1; // Allow for combinational logic to settle
            if (wb0_a !== expected_wb0_a || wb0_b !== expected_wb0_b || wb1_a !== expected_wb1_a || wb1_b !== expected_wb1_b) begin
                $display("ERROR @ Time=%0t", $time);
                if (wb0_a !== expected_wb0_a) $display("  wb0_a = %h (expected %h)", wb0_a, expected_wb0_a);
                if (wb0_b !== expected_wb0_b) $display("  wb0_b = %h (expected %h)", wb0_b, expected_wb0_b);
                if (wb1_a !== expected_wb1_a) $display("  wb1_a = %h (expected %h)", wb1_a, expected_wb1_a);
                if (wb1_b !== expected_wb1_b) $display("  wb1_b = %h (expected %h)", wb1_b, expected_wb1_b);
                errors = errors + 1;
            end
        end
    endtask

    initial begin
        // Initialize Inputs
        D = 0;
        WA0 = 0;
        WA1 = 0;

        $dumpfile("tb_verify_cim_array.vcd");
        $dumpvars(0, tb_verify_cim_array);
        #1;

        // Test Case 1: Write to bank 0 and verify
        $display("--- Test Case 1: Write to bank 0 and verify ---");
        for (i = 0; i < 8; i = i + 1) begin
            WA0 = 1 << i;
            WA1 = 8'b0;
            D = {12'h100 + i, 12'hA00 + i};
            #10;
            case (i)
                0: check_output(96'hfffffffffffffffffffff5ff, 96'hffffffffffffffffffffffff, 96'hffffffffffffffffffffffff, 96'hffffffffffffffffffffffff);
                1: check_output(96'hffffffffffffffffff5fe5ff, 96'hffffffffffffffffffffffff, 96'hffffffffffffffffffffffff, 96'hffffffffffffffffffffffff);
                2: check_output(96'hfffffffffffffff5fd5fe5ff, 96'hffffffffffffffffffffffff, 96'hffffffffffffffffffffffff, 96'hffffffffffffffffffffffff);
                3: check_output(96'hffffffffffff5fc5fd5fe5ff, 96'hffffffffffffffffffffffff, 96'hffffffffffffffffffffffff, 96'hffffffffffffffffffffffff);
                4: check_output(96'hfffffffff5fb5fc5fd5fe5ff, 96'hffffffffffffffffffffffff, 96'hffffffffffffffffffffffff, 96'hffffffffffffffffffffffff);
                5: check_output(96'hffffff5fa5fb5fc5fd5fe5ff, 96'hffffffffffffffffffffffff, 96'hffffffffffffffffffffffff, 96'hffffffffffffffffffffffff);
                6: check_output(96'hfff5f95fa5fb5fc5fd5fe5ff, 96'hffffffffffffffffffffffff, 96'hffffffffffffffffffffffff, 96'hffffffffffffffffffffffff);
                7: check_output(96'h5f85f95fa5fb5fc5fd5fe5ff, 96'hffffffffffffffffffffffff, 96'hffffffffffffffffffffffff, 96'hffffffffffffffffffffffff);
            endcase
        end
        WA0 = 8'b0;
        #10;
        check_output(96'h5f85f95fa5fb5fc5fd5fe5ff, 96'hffffffffffffffffffffffff, 96'hffffffffffffffffffffffff, 96'hffffffffffffffffffffffff);

        // Test Case 2: Write to bank 1 and verify
        $display("--- Test Case 2: Write to bank 1 and verify ---");
        for (i = 0; i < 8; i = i + 1) begin
            WA0 = 8'b0;
            WA1 = 1 << i;
            D = {12'h200 + i, 12'hB00 + i};
            #10;
            case (i)
                0: check_output(96'h5f85f95fa5fb5fc5fd5fe5ff, 96'hffffffffffffffffffffffff, 96'hfffffffffffffffffffff4ff, 96'hffffffffffffffffffffffff);
                1: check_output(96'h5f85f95fa5fb5fc5fd5fe5ff, 96'hffffffffffffffffffffffff, 96'hffffffffffffffffff4fe4ff, 96'hffffffffffffffffffffffff);
                2: check_output(96'h5f85f95fa5fb5fc5fd5fe5ff, 96'hffffffffffffffffffffffff, 96'hfffffffffffffff4fd4fe4ff, 96'hffffffffffffffffffffffff);
                3: check_output(96'h5f85f95fa5fb5fc5fd5fe5ff, 96'hffffffffffffffffffffffff, 96'hffffffffffff4fc4fd4fe4ff, 96'hffffffffffffffffffffffff);
                4: check_output(96'h5f85f95fa5fb5fc5fd5fe5ff, 96'hffffffffffffffffffffffff, 96'hfffffffff4fb4fc4fd4fe4ff, 96'hffffffffffffffffffffffff);
                5: check_output(96'h5f85f95fa5fb5fc5fd5fe5ff, 96'hffffffffffffffffffffffff, 96'hffffff4fa4fb4fc4fd4fe4ff, 96'hffffffffffffffffffffffff);
                6: check_output(96'h5f85f95fa5fb5fc5fd5fe5ff, 96'hffffffffffffffffffffffff, 96'hfff4f94fa4fb4fc4fd4fe4ff, 96'hffffffffffffffffffffffff);
                7: check_output(96'h5f85f95fa5fb5fc5fd5fe5ff, 96'hffffffffffffffffffffffff, 96'h4f84f94fa4fb4fc4fd4fe4ff, 96'hffffffffffffffffffffffff);
            endcase
        end
        WA1 = 8'b0;
        #10;
        check_output(96'h5f85f95fa5fb5fc5fd5fe5ff, 96'hffffffffffffffffffffffff, 96'h4f84f94fa4fb4fc4fd4fe4ff, 96'hffffffffffffffffffffffff);

        // Test Case 3: Overwrite data in bank 0
        $display("--- Test Case 3: Overwrite data in bank 0 ---");
        WA0 = 1 << 3; // Address 3
        WA1 = 8'b0;
        D = 24'hDEADBE;
        #10;
        check_output(96'h5f85f95fa5fb2415fd5fe5ff, 96'hffffffffffff215fffffffff, 96'h4f84f94fa4fb4fc4fd4fe4ff, 96'hffffffffffffffffffffffff);
        WA0 = 8'b0;
        #10;
        check_output(96'h5f85f95fa5fb2415fd5fe5ff, 96'hffffffffffff215fffffffff, 96'h4f84f94fa4fb4fc4fd4fe4ff, 96'hffffffffffffffffffffffff);

        // Final result
        #20;
        if (errors == 0)
            $display("--- VERIFICATION PASSED ---");
        else
            $display("--- VERIFICATION FAILED: %0d errors ---", errors);

        $finish;
    end

endmodule

DCIM_Macro/tb_verify_cim_array.vcd
$date
	Sat Aug 09 02:11:28 2025
$end
$version
	Icarus Verilog
$end
$timescale
	1ps
$end
$scope module tb_verify_cim_array $end
$var wire 96 ! wb1_b [95:0] $end
$var wire 96 " wb1_a [95:0] $end
$var wire 96 # wb0_b [95:0] $end
$var wire 96 $ wb0_a [95:0] $end
$var reg 24 % D [23:0] $end
$var reg 8 & WA0 [7:0] $end
$var reg 8 ' WA1 [7:0] $end
$var integer 32 ( errors [31:0] $end
$var integer 32 ) i [31:0] $end
$scope module uut $end
$var wire 24 * D [23:0] $end
$var wire 8 + WA0 [7:0] $end
$var wire 8 , WA1 [7:0] $end
$var wire 96 - wb1_b [95:0] $end
$var wire 96 . wb1_a [95:0] $end
$var wire 96 / wb0_b [95:0] $end
$var wire 96 0 wb0_a [95:0] $end
$scope module bank0_inst $end
$var wire 24 1 D [23:0] $end
$var wire 8 2 WA [7:0] $end
$var wire 96 3 wb_a [95:0] $end
$var wire 96 4 wb_b [95:0] $end
$var integer 32 5 i [31:0] $end
$upscope $end
$scope module bank1_inst $end
$var wire 24 6 D [23:0] $end
$var wire 8 7 WA [7:0] $end
$var wire 96 8 wb_a [95:0] $end
$var wire 96 9 wb_b [95:0] $end
$var integer 32 : i [31:0] $end
$upscope $end
$upscope $end
$scope task check_output $end
$var reg 96 ; expected_wb0_a [95:0] $end
$var reg 96 < expected_wb0_b [95:0] $end
$var reg 96 = expected_wb1_a [95:0] $end
$var reg 96 > expected_wb1_b [95:0] $end
$upscope $end
$upscope $end
$enddefinitions $end
$comment Show the parameter values. $end
$dumpall
$end
#0
$dumpvars
bx >
bx =
bx <
bx ;
b1000 :
b111111111111111111111111111111111111111111111111111111111111111111111111111111111111111111111111 9
b111111111111111111111111111111111111111111111111111111111111111111111111111111111111111111111111 8
b0 7
b0 6
b1000 5
b111111111111111111111111111111111111111111111111111111111111111111111111111111111111111111111111 4
b111111111111111111111111111111111111111111111111111111111111111111111111111111111111111111111111 3
b0 2
b0 1
b111111111111111111111111111111111111111111111111111111111111111111111111111111111111111111111111 0
b111111111111111111111111111111111111111111111111111111111111111111111111111111111111111111111111 /
b111111111111111111111111111111111111111111111111111111111111111111111111111111111111111111111111 .
b111111111111111111111111111111111111111111111111111111111111111111111111111111111111111111111111 -
b0 ,
b0 +
b0 *
bx )
b0 (
b0 '
b0 &
b0 %
b111111111111111111111111111111111111111111111111111111111111111111111111111111111111111111111111 $
b111111111111111111111111111111111111111111111111111111111111111111111111111111111111111111111111 #
b111111111111111111111111111111111111111111111111111111111111111111111111111111111111111111111111 "
b111111111111111111111111111111111111111111111111111111111111111111111111111111111111111111111111 !
$end
#1000
b111111111111111111111111111111111111111111111111111111111111111111111111111111111111010111111111 $
b111111111111111111111111111111111111111111111111111111111111111111111111111111111111010111111111 0
b111111111111111111111111111111111111111111111111111111111111111111111111111111111111010111111111 3
b101000000000 %
b101000000000 *
b101000000000 1
b101000000000 6
b1 &
b1 +
b1 2
b0 )
#11000
b111111111111111111111111111111111111111111111111111111111111111111111111111111111111111111111111 >
b111111111111111111111111111111111111111111111111111111111111111111111111111111111111111111111111 =
b111111111111111111111111111111111111111111111111111111111111111111111111111111111111111111111111 <
b111111111111111111111111111111111111111111111111111111111111111111111111111111111111010111111111 ;
#12000
b111111111111111111111111111111111111111111111111111111111111111111111111010111111110010111111111 $
b111111111111111111111111111111111111111111111111111111111111111111111111010111111110010111111111 0
b111111111111111111111111111111111111111111111111111111111111111111111111010111111110010111111111 3
b101000000001 %
b101000000001 *
b101000000001 1
b101000000001 6
b10 &
b10 +
b10 2
b1 )
#22000
b111111111111111111111111111111111111111111111111111111111111111111111111010111111110010111111111 ;
#23000
b111111111111111111111111111111111111111111111111111111111111010111111101010111111110010111111111 $
b111111111111111111111111111111111111111111111111111111111111010111111101010111111110010111111111 0
b111111111111111111111111111111111111111111111111111111111111010111111101010111111110010111111111 3
b101000000010 %
b101000000010 *
b101000000010 1
b101000000010 6
b100 &
b100 +
b100 2
b10 )
#33000
b111111111111111111111111111111111111111111111111111111111111010111111101010111111110010111111111 ;
#34000
b111111111111111111111111111111111111111111111111010111111100010111111101010111111110010111111111 $
b111111111111111111111111111111111111111111111111010111111100010111111101010111111110010111111111 0
b111111111111111111111111111111111111111111111111010111111100010111111101010111111110010111111111 3
b101000000011 %
b101000000011 *
b101000000011 1
b101000000011 6
b1000 &
b1000 +
b1000 2
b11 )
#44000
b111111111111111111111111111111111111111111111111010111111100010111111101010111111110010111111111 ;
#45000
b111111111111111111111111111111111111010111111011010111111100010111111101010111111110010111111111 $
b111111111111111111111111111111111111010111111011010111111100010111111101010111111110010111111111 0
b111111111111111111111111111111111111010111111011010111111100010111111101010111111110010111111111 3
b101000000100 %
b101000000100 *
b101000000100 1
b101000000100 6
b10000 &
b10000 +
b10000 2
b100 )
#55000
b111111111111111111111111111111111111010111111011010111111100010111111101010111111110010111111111 ;
#56000
b111111111111111111111111010111111010010111111011010111111100010111111101010111111110010111111111 $
b111111111111111111111111010111111010010111111011010111111100010111111101010111111110010111111111 0
b111111111111111111111111010111111010010111111011010111111100010111111101010111111110010111111111 3
b101000000101 %
b101000000101 *
b101000000101 1
b101000000101 6
b100000 &
b100000 +
b100000 2
b101 )
#66000
b111111111111111111111111010111111010010111111011010111111100010111111101010111111110010111111111 ;
#67000
b111111111111010111111001010111111010010111111011010111111100010111111101010111111110010111111111 $
b111111111111010111111001010111111010010111111011010111111100010111111101010111111110010111111111 0
b111111111111010111111001010111111010010111111011010111111100010111111101010111111110010111111111 3
b101000000110 %
b101000000110 *
b101000000110 1
b101000000110 6
b1000000 &
b1000000 +
b1000000 2
b110 )
#77000
b111111111111010111111001010111111010010111111011010111111100010111111101010111111110010111111111 ;
#78000
b10111111000010111111001010111111010010111111011010111111100010111111101010111111110010111111111 $
b10111111000010111111001010111111010010111111011010111111100010111111101010111111110010111111111 0
b10111111000010111111001010111111010010111111011010111111100010111111101010111111110010111111111 3
b101000000111 %
b101000000111 *
b101000000111 1
b101000000111 6
b10000000 &
b10000000 +
b10000000 2
b111 )
#88000
b10111111000010111111001010111111010010111111011010111111100010111111101010111111110010111111111 ;
#89000
b0 &
b0 +
b0 2
b1000 )
#100000
b111111111111111111111111111111111111111111111111111111111111111111111111111111111111010011111111 "
b111111111111111111111111111111111111111111111111111111111111111111111111111111111111010011111111 .
b111111111111111111111111111111111111111111111111111111111111111111111111111111111111010011111111 8
b101100000000 %
b101100000000 *
b101100000000 1
b101100000000 6
b1 '
b1 ,
b1 7
b0 )
#110000
b111111111111111111111111111111111111111111111111111111111111111111111111111111111111010011111111 =
#111000
b111111111111111111111111111111111111111111111111111111111111111111111111010011111110010011111111 "
b111111111111111111111111111111111111111111111111111111111111111111111111010011111110010011111111 .
b111111111111111111111111111111111111111111111111111111111111111111111111010011111110010011111111 8
b101100000001 %
b101100000001 *
b101100000001 1
b101100000001 6
b10 '
b10 ,
b10 7
b1 )
#121000
b111111111111111111111111111111111111111111111111111111111111111111111111010011111110010011111111 =
#122000
b111111111111111111111111111111111111111111111111111111111111010011111101010011111110010011111111 "
b111111111111111111111111111111111111111111111111111111111111010011111101010011111110010011111111 .
b111111111111111111111111111111111111111111111111111111111111010011111101010011111110010011111111 8
b101100000010 %
b101100000010 *
b101100000010 1
b101100000010 6
b100 '
b100 ,
b100 7
b10 )
#132000
b111111111111111111111111111111111111111111111111111111111111010011111101010011111110010011111111 =
#133000
b111111111111111111111111111111111111111111111111010011111100010011111101010011111110010011111111 "
b111111111111111111111111111111111111111111111111010011111100010011111101010011111110010011111111 .
b111111111111111111111111111111111111111111111111010011111100010011111101010011111110010011111111 8
b101100000011 %
b101100000011 *
b101100000011 1
b101100000011 6
b1000 '
b1000 ,
b1000 7
b11 )
#143000
b111111111111111111111111111111111111111111111111010011111100010011111101010011111110010011111111 =
#144000
b111111111111111111111111111111111111010011111011010011111100010011111101010011111110010011111111 "
b111111111111111111111111111111111111010011111011010011111100010011111101010011111110010011111111 .
b111111111111111111111111111111111111010011111011010011111100010011111101010011111110010011111111 8
b101100000100 %
b101100000100 *
b101100000100 1
b101100000100 6
b10000 '
b10000 ,
b10000 7
b100 )
#154000
b111111111111111111111111111111111111010011111011010011111100010011111101010011111110010011111111 =
#155000
b111111111111111111111111010011111010010011111011010011111100010011111101010011111110010011111111 "
b111111111111111111111111010011111010010011111011010011111100010011111101010011111110010011111111 .
b111111111111111111111111010011111010010011111011010011111100010011111101010011111110010011111111 8
b101100000101 %
b101100000101 *
b101100000101 1
b101100000101 6
b100000 '
b100000 ,
b100000 7
b101 )
#165000
b111111111111111111111111010011111010010011111011010011111100010011111101010011111110010011111111 =
#166000
b111111111111010011111001010011111010010011111011010011111100010011111101010011111110010011111111 "
b111111111111010011111001010011111010010011111011010011111100010011111101010011111110010011111111 .
b111111111111010011111001010011111010010011111011010011111100010011111101010011111110010011111111 8
b101100000110 %
b101100000110 *
b101100000110 1
b101100000110 6
b1000000 '
b1000000 ,
b1000000 7
b110 )
#176000
b111111111111010011111001010011111010010011111011010011111100010011111101010011111110010011111111 =
#177000
b10011111000010011111001010011111010010011111011010011111100010011111101010011111110010011111111 "
b10011111000010011111001010011111010010011111011010011111100010011111101010011111110010011111111 .
b10011111000010011111001010011111010010011111011010011111100010011111101010011111110010011111111 8
b101100000111 %
b101100000111 *
b101100000111 1
b101100000111 6
b10000000 '
b10000000 ,
b10000000 7
b111 )
#187000
b10011111000010011111001010011111010010011111011010011111100010011111101010011111110010011111111 =
#188000
b0 '
b0 ,
b0 7
b1000 )
#199000
b10111111000010111111001010111111010010111111011001001000001010111111101010111111110010111111111 $
b10111111000010111111001010111111010010111111011001001000001010111111101010111111110010111111111 0
b10111111000010111111001010111111010010111111011001001000001010111111101010111111110010111111111 3
b111111111111111111111111111111111111111111111111001000010101111111111111111111111111111111111111 #
b111111111111111111111111111111111111111111111111001000010101111111111111111111111111111111111111 /
b111111111111111111111111111111111111111111111111001000010101111111111111111111111111111111111111 4
b110111101010110110111110 %
b110111101010110110111110 *
b110111101010110110111110 1
b110111101010110110111110 6
b1000 &
b1000 +
b1000 2
#209000
b111111111111111111111111111111111111111111111111001000010101111111111111111111111111111111111111 <
b10111111000010111111001010111111010010111111011001001000001010111111101010111111110010111111111 ;
#210000
b0 &
b0 +
b0 2
