DCIM_Macro/rtl/add.v
module add #(
    parameter width = 12      // 默认位宽为12
)(
    input [width-1:0] a,      // 输入a
    input [width-1:0] b,      // 输入b
    input sus,                // 有符号/无符号控制
    output wire [width:0] sum // 加法结果
);

    // 有符号加法：进行符号位扩展
    wire [width:0] a_signed, b_signed;
    
    // 根据sus信号决定是否进行符号扩展
    assign a_signed = sus ? {a[width-1], a} : {1'b0, a};
    assign b_signed = sus ? {b[width-1], b} : {1'b0, b};
    
    // 执行加法
    assign sum = a_signed + b_signed;

endmodule

DCIM_Macro/tb_verify/tb_verify_add.v
`timescale 1ns / 1ps

module tb_verify_add;

    // Parameters
    localparam width = 12;

    // Inputs
    reg signed [width-1:0] a;  // 声明为有符号类型
    reg signed [width-1:0] b;   // 声明为有符号类型
    reg sus;

    // Outputs
    wire signed [width:0] sum;  // 声明为有符号类型

    // Instantiate the Unit Under Test (UUT)
    add #(.width(width)) uut (
        .a(a),
        .b(b),
        .sus(sus),
        .sum(sum)
    );

    integer errors = 0;

    initial begin
        // Initialize Inputs
        a = 0;
        b = 0;
        sus = 0;

        $dumpfile("tb_verify_add.vcd");
        $dumpvars(0, tb_verify_add);

        // --- Verification Case 1: Unsigned Addition (sus = 0) ---
        $display("--- Verification Case 1: Unsigned Addition (sus = 0) ---");
        sus = 0;
        a = 12'd10; b = 12'd20; #10; 
        if (sum !== 13'd30) begin
            errors = errors + 1;
            $display("Error: %d + %d = %d (expected 30)", a, b, sum);
        end
        
        a = 12'd4095; b = 12'd1; #10; 
        if (sum !== 13'd4096) begin
            errors = errors + 1;
            $display("Error: %d + %d = %d (expected 4096)", a, b, sum);
        end
        
        a = 12'hFFF; b = 12'hFFF; #10; 
        if (sum !== 13'h1FFE) begin
            errors = errors + 1;
            $display("Error: %h + %h = %h (expected 1FFE)", a, b, sum);
        end
        
        a = 12'h000; b = 12'h000; #10; 
        if (sum !== 13'd0) begin
            errors = errors + 1;
            $display("Error: %d + %d = %d (expected 0)", a, b, sum);
        end

        // --- Verification Case 2: Signed Addition (sus = 1) ---
        $display("--- Verification Case 2: Signed Addition (sus = 1) ---");
        sus = 1;
        
        // 正数+正数
        a = 12'sd10; b = 12'sd20; #10; 
        if (sum !== 13'sd30) begin 
            errors = errors + 1;
            $display("Error: %d + %d = %d (expected 30)", a, b, sum);
        end
        
        // 负数+正数
        a = -12'sd10; b = 12'sd20; #10; 
        if (sum !== 13'sd10) begin 
            errors = errors + 1;
            $display("Error: %d + %d = %d (expected 10)", a, b, sum);
        end
        
        // 正数+负数
        a = 12'sd10; b = -12'sd20; #10; 
        if (sum !== -13'sd10) begin 
            errors = errors + 1;
            $display("Error: %d + %d = %d (expected -10)", a, b, sum);
        end
        
        // 负数+负数
        a = -12'sd10; b = -12'sd20; #10; 
        if (sum !== -13'sd30) begin 
            errors = errors + 1;
            $display("Error: %d + %d = %d (expected -30)", a, b, sum);
        end
        
        // 边界测试
        a = 12'sd2047; b = 12'sd1; #10; 
        if (sum !== 13'sd2048) begin 
            errors = errors + 1;
            $display("Error: %d + %d = %d (expected 2048)", a, b, sum);
        end
        
        a = -12'sd2048; b = -12'sd1; #10; 
        if (sum !== -13'sd2049) begin 
            errors = errors + 1;
            $display("Error: %d + %d = %d (expected -2049)", a, b, sum);
        end
        
        a = 12'sh7FF; b = 12'sh7FF; #10; 
        if (sum !== 13'shFFE) begin 
            errors = errors + 1;
            $display("Error: %h + %h = %h (expected FFE)", a, b, sum);
        end
        
        a = 12'sh800; b = 12'sh800; #10; 
        if (sum !== 13'sh1000) begin 
            errors = errors + 1;
            $display("Error: %h + %h = %h (expected 1000)", a, b, sum);
        end

        // Final result
        #20;
        if (errors == 0)
            $display("--- VERIFICATION PASSED ---");
        else
            $display("--- VERIFICATION FAILED: %0d errors ---", errors);

        $finish;
    end

endmodule

DCIM_Macro/tb_verify_add.vcd
$date
	Sat Aug 09 02:11:15 2025
$end
$version
	Icarus Verilog
$end
$timescale
	1ps
$end
$scope module tb_verify_add $end
$var wire 13 ! sum [12:0] $end
$var parameter 32 " width $end
$var reg 12 # a [11:0] $end
$var reg 12 $ b [11:0] $end
$var reg 1 % sus $end
$var integer 32 & errors [31:0] $end
$scope module uut $end
$var wire 12 ' a [11:0] $end
$var wire 12 ( b [11:0] $end
$var wire 1 % sus $end
$var wire 13 ) sum [12:0] $end
$var wire 13 * b_signed [12:0] $end
$var wire 13 + a_signed [12:0] $end
$var parameter 32 , width $end
$upscope $end
$upscope $end
$enddefinitions $end
$comment Show the parameter values. $end
$dumpall
b1100 ,
b1100 "
$end
#0
$dumpvars
b1010 +
b10100 *
b11110 )
b10100 (
b1010 '
b0 &
0%
b10100 $
b1010 #
b11110 !
$end
#10000
b1 *
b1000000000000 !
b1000000000000 )
b111111111111 +
b1 $
b1 (
b111111111111 #
b111111111111 '
#20000
b1111111111110 !
b1111111111110 )
b111111111111 *
b111111111111 $
b111111111111 (
#30000
b0 *
b0 !
b0 )
b0 +
b0 $
b0 (
b0 #
b0 '
#40000
b1010 +
b11110 !
b11110 )
b10100 *
b10100 $
b10100 (
b1010 #
b1010 '
1%
#50000
b1010 !
b1010 )
b1111111110110 +
b111111110110 #
b111111110110 '
#60000
b1111111101100 *
b1111111110110 !
b1111111110110 )
b1010 +
b111111101100 $
b111111101100 (
b1010 #
b1010 '
#70000
b1111111100010 !
b1111111100010 )
b1111111110110 +
b111111110110 #
b111111110110 '
#80000
b1 *
b100000000000 !
b100000000000 )
b11111111111 +
b1 $
b1 (
b11111111111 #
b11111111111 '
#90000
b1111111111111 *
b1011111111111 !
b1011111111111 )
b1100000000000 +
b111111111111 $
b111111111111 (
b100000000000 #
b100000000000 '
#100000
b11111111111 *
b111111111110 !
b111111111110 )
b11111111111 +
b11111111111 $
b11111111111 (
b11111111111 #
b11111111111 '
#110000
b1100000000000 *
b1000000000000 !
b1000000000000 )
b1100000000000 +
b100000000000 $
b100000000000 (
b100000000000 #
b100000000000 '
